[{"datasetid": "catalogue-de-messier", "recordid": "74dd035b8e3f0939adc7fdf89ec6212ab6b185d2", "fields": {"objet": "Open Cluster / Amas Ouvert", "const": "Per", "mag": 5, "decouvreur": "Messier", "distance": 1450, "image": "http://www.lasam.ca/messier/M034.JPG", "ngc": "NGC 1039", "latin_name_nom_latin": "Perseus", "messier": "M34", "image_url": {"mimetype": "image/jpeg", "format": "JPEG", "color_summary": ["rgba(213, 213, 213, 1.00)", "rgba(245, 245, 245, 1.00)", "rgba(250, 250, 250, 1.00)"], "filename": "M034.JPG.jpe", "width": 816, "id": "f77873064c67256350aa5817915fe480", "height": 1054, "thumbnail": true}, "saison": "Autumn / Automne", "english_name_nom_en_anglais": "Perseus", "french_name_nom_francais": "Pers\u00e9e", "annee": "1764", "dec": "+42:44:46.1", "dimension": "35,0'", "ra": "02:42:07.40"}, "record_timestamp": "2019-03-05T10:44:29.021+01:00"},{"datasetid": "catalogue-de-messier", "recordid": "b58c3798522520b494e3b482bce8e01b9a6031bb", "fields": {"objet": "Globular Cluster / Amas Globulaire", "const": "Lyr", "mag": 8, "decouvreur": "Messier", "distance": 45600, "image": "http://www.lasam.ca/messier/M056.JPG", "ngc": "NGC 6779", "latin_name_nom_latin": "Lyra", "messier": "M56", "image_url": {"mimetype": "image/jpeg", "format": "JPEG", "color_summary": ["rgba(217, 217, 217, 1.00)", "rgba(215, 214, 214, 1.00)", "rgba(222, 221, 221, 1.00)"], "filename": "M056.JPG.jpe", "width": 816, "id": "6f114f36addc2958e48cdaa537814ccd", "height": 1054, "thumbnail": true}, "saison": "Summer / \u00c9t\u00e9", "english_name_nom_en_anglais": "Lyre", "french_name_nom_francais": "Lyre", "annee": "1779", "dec": "+30:11:04.2", "dimension": "2,4'", "ra": "19:16:35.51"}, "record_timestamp": "2019-03-05T10:44:29.021+01:00"},{"datasetid": "catalogue-de-messier", "recordid": "9588bfcb157762a61ec87d7bfe9819cef8502938", "fields": {"objet": "Galaxy / Galaxie", "const": "UMa", "mag": 9, "decouvreur": "M\u00e9chain", "distance": 27000000, "image": "http://www.lasam.ca/messier/M109.JPG", "ngc": "NGC 3992", "latin_name_nom_latin": "Ursa Major", "messier": "M109", "image_url": {"mimetype": "image/jpeg", "format": "JPEG", "color_summary": ["rgba(240, 240, 240, 1.00)", "rgba(252, 252, 252, 1.00)", "rgba(250, 250, 250, 1.00)"], "filename": "M109.JPG.jpe", "width": 816, "id": "ec85cad083cafcaf2030144edbf280d7", "height": 1054, "thumbnail": true}, "saison": "Autumn / Automne", "english_name_nom_en_anglais": "Big Bear", "french_name_nom_francais": "Grande Ourse", "annee": "1782", "dec": "+53:22:28.3", "dimension": "7,6' x 4,9'", "ra": "11:57:35.98"}, "record_timestamp": "2019-03-05T10:44:29.021+01:00"},{"datasetid": "catalogue-de-messier", "recordid": "4d5d402e83ef5f53ca8df305b781724e7898350c", "fields": {"objet": "Galaxy / Galaxie", "const": "And", "mag": 8, "decouvreur": "Messier", "distance": 2250000, "image": "http://www.lasam.ca/messier/M110.JPG", "ngc": "NGC 205", "latin_name_nom_latin": "Andromeda", "messier": "M110", "image_url": {"mimetype": "image/jpeg", "format": "JPEG", "color_summary": ["rgba(217, 217, 217, 1.00)", "rgba(252, 252, 252, 1.00)", "rgba(249, 248, 248, 1.00)"], "filename": "M110.JPG.jpe", "width": 816, "id": "846fe85c601053437fe9497d9eb6c522", "height": 1054, "thumbnail": true}, "saison": "Autumn / Automne", "english_name_nom_en_anglais": "Andromeda", "french_name_nom_francais": "Androm\u00e8de", "annee": "1773", "dec": "+41:41:07.1", "dimension": "17,0, x 9,8'", "ra": "00:40:22.08"}, "record_timestamp": "2019-03-05T10:44:29.021+01:00"},{"datasetid": "catalogue-de-messier", "recordid": "175a62ddc515be7ad77106908aba59e8caf5aa03", "fields": {"objet": "Globular Cluster / Amas Globulaire", "const": "Oph", "mag": 7, "decouvreur": "Messier", "distance": 25800, "image": "http://www.lasam.ca/messier/M009.JPG", "ngc": "NGC 6333", "latin_name_nom_latin": "Ophiuchus", "messier": "M9", "image_url": {"mimetype": "image/jpeg", "format": "JPEG", "color_summary": ["rgba(241, 240, 240, 1.00)", "rgba(211, 209, 210, 1.00)", "rgba(188, 187, 188, 1.00)"], "filename": "M009.JPG.jpe", "width": 816, "id": "5f5ace9ee1c128a336b845ef0262e69c", "height": 1054, "thumbnail": true}, "saison": "Summer / \u00c9t\u00e9", "english_name_nom_en_anglais": "Serpent Holder", "french_name_nom_francais": "Ophiuchus", "annee": "1764", "dec": "-18:30:58.5", "dimension": "5,5'", "ra": "17:19:11.78"}, "record_timestamp": "2019-03-05T10:44:29.021+01:00"},{"datasetid": "catalogue-de-messier", "recordid": "474a5c477d3fb4561ce50db7a500b658d4276ab5", "fields": {"objet": "Supernova remnant / Reste de Supernova", "const": "Tau", "mag": 8, "decouvreur": "B\u00e9vis", "distance": 6500, "image": "http://www.lasam.ca/messier/M001.JPG", "ngc": "NGC 1952", "latin_name_nom_latin": "Taurus", "messier": "M1", "image_url": {"mimetype": "image/jpeg", "format": "JPEG", "color_summary": ["rgba(201, 201, 201, 1.00)", "rgba(220, 219, 219, 1.00)", "rgba(225, 224, 225, 1.00)"], "filename": "M001.JPG.jpe", "width": 816, "id": "9e2732e960c78804a2ee3fa059c69231", "height": 1054, "thumbnail": true}, "saison": "Winter / Hiver", "english_name_nom_en_anglais": "Bull", "french_name_nom_francais": "Taureau", "annee": "1731", "dec": "+22:00:52.1", "dimension": "6,0' x 4,0'", "ra": "05:34:31.97"}, "record_timestamp": "2019-03-05T10:44:29.021+01:00"},{"datasetid": "catalogue-de-messier", "recordid": "cd02f3ce6e628f66bea762a6897242cd1cea582c", "fields": {"objet": "Globular Cluster / Amas Globulaire", "const": "Sgr", "mag": 5, "decouvreur": "Ihle", "distance": 7800, "image": "http://www.lasam.ca/messier/M022.JPG", "ngc": "NGC 6656", "latin_name_nom_latin": "Sagittarius", "messier": "M22", "image_url": {"mimetype": "image/jpeg", "format": "JPEG", "color_summary": ["rgba(196, 195, 195, 1.00)", "rgba(194, 192, 193, 1.00)", "rgba(197, 196, 196, 1.00)"], "filename": "M022.JPG.jpe", "width": 816, "id": "ae30dc0b097efe181077683d076f675c", "height": 1054, "thumbnail": true}, "saison": "Summer / \u00c9t\u00e9", "english_name_nom_en_anglais": "Archer", "french_name_nom_francais": "Sagittaire", "annee": "1665", "dec": "-23:54:12.3", "dimension": "17,0'", "ra": "18:36:24.20"}, "record_timestamp": "2019-03-05T10:44:29.021+01:00"},{"datasetid": "catalogue-de-messier", "recordid": "4e3de8cdf703e90ffff2bb163d435c95638fdc31", "fields": {"objet": "Globular Cluster / Amas Globulaire", "const": "Cap", "mag": 7, "decouvreur": "Messier", "distance": 41000, "image": "http://www.lasam.ca/messier/M030.JPG", "ngc": "NGC 7099", "latin_name_nom_latin": "Capricornus", "messier": "M30", "image_url": {"mimetype": "image/jpeg", "format": "JPEG", "color_summary": ["rgba(240, 239, 239, 1.00)", "rgba(252, 252, 252, 1.00)", "rgba(250, 250, 250, 1.00)"], "filename": "M030.JPG.jpe", "width": 816, "id": "d8dec275d51809c5e4ac837cb5e29015", "height": 1054, "thumbnail": true}, "saison": "Autumn / Automne", "english_name_nom_en_anglais": "Goat", "french_name_nom_francais": "Capricorne", "annee": "1764", "dec": "-23:10:44.7", "dimension": "8,9'", "ra": "21:40:22.02"}, "record_timestamp": "2019-03-05T10:44:29.021+01:00"},{"datasetid": "catalogue-de-messier", "recordid": "12b793e3c681416a14a75b9d898109a3bb033bcf", "fields": {"objet": "Globular Cluster / Amas Globulaire", "const": "Oph", "mag": 6, "decouvreur": "Messier", "distance": 18900, "image": "http://www.lasam.ca/messier/M012.JPG", "ngc": "NGC 6218", "latin_name_nom_latin": "Ophiuchus", "messier": "M12", "image_url": {"mimetype": "image/jpeg", "format": "JPEG", "color_summary": ["rgba(241, 240, 240, 1.00)", "rgba(254, 253, 253, 1.00)", "rgba(243, 242, 242, 1.00)"], "filename": "M012.JPG.jpe", "width": 816, "id": "686b853d137708ef283311e638592387", "height": 1054, "thumbnail": true}, "saison": "Summer / \u00c9t\u00e9", "english_name_nom_en_anglais": "Serpent Holder", "french_name_nom_francais": "Ophiuchus", "annee": "1764", "dec": "-01:56:52.2", "dimension": "12,2'", "ra": "16:47:14.52"}, "record_timestamp": "2019-03-05T10:44:29.021+01:00"},{"datasetid": "catalogue-de-messier", "recordid": "58873094dea8a324acb3e883dbea07f3489b7dcd", "fields": {"objet": "Globular Cluster / Amas Globulaire", "const": "Her", "mag": 5, "decouvreur": "Halley", "distance": 23500, "image": "http://www.lasam.ca/messier/M013.JPG", "ngc": "NGC 6205", "latin_name_nom_latin": "Hercules", "messier": "M13", "image_url": {"mimetype": "image/jpeg", "format": "JPEG", "color_summary": ["rgba(242, 241, 241, 1.00)", "rgba(252, 252, 252, 1.00)", "rgba(249, 249, 249, 1.00)"], "filename": "M013.JPG.jpe", "width": 816, "id": "50043671892eb3ae293cac3cb5fd0cab", "height": 1054, "thumbnail": true}, "saison": "Summer / \u00c9t\u00e9", "english_name_nom_en_anglais": "Hercules", "french_name_nom_francais": "Hercule", "annee": "1714", "dec": "+36:27:40.7", "dimension": "23,2'", "ra": "16:41:41.63"}, "record_timestamp": "2019-03-05T10:44:29.021+01:00"},{"datasetid": "catalogue-de-messier", "recordid": "8dbc0bc4381a046881153ff7e57d8ec595d4fcb2", "fields": {"objet": "Globular Cluster / Amas Globulaire", "const": "Oph", "mag": 7, "decouvreur": "Messier", "distance": 22500, "image": "http://www.lasam.ca/messier/M019.JPG", "ngc": "NGC 6273", "latin_name_nom_latin": "Ophiuchus", "messier": "M19", "image_url": {"mimetype": "image/jpeg", "format": "JPEG", "color_summary": ["rgba(216, 215, 215, 1.00)", "rgba(203, 202, 203, 1.00)", "rgba(201, 200, 200, 1.00)"], "filename": "M019.JPG.jpe", "width": 816, "id": "f38fcadac00a438f2d62eb1fe18d0a21", "height": 1054, "thumbnail": true}, "saison": "Summer / \u00c9t\u00e9", "english_name_nom_en_anglais": "Serpent Holder", "french_name_nom_francais": "Ophiuchus", "annee": "1764", "dec": "-26:16:04.6", "dimension": "5,3'", "ra": "17:02:37.68"}, "record_timestamp": "2019-03-05T10:44:29.021+01:00"},{"datasetid": "catalogue-de-messier", "recordid": "e89adad0ccd1776cff70ebdef7513c472d3f555f", "fields": {"objet": "Open Cluster / Amas Ouvert", "const": "Sct", "mag": 8, "decouvreur": "Le Gentil", "distance": 5100, "image": "http://www.lasam.ca/messier/M026.JPG", "ngc": "NGC 6694", "latin_name_nom_latin": "Scutum", "messier": "M26", "image_url": {"mimetype": "image/jpeg", "format": "JPEG", "color_summary": ["rgba(205, 204, 204, 1.00)", "rgba(213, 212, 212, 1.00)", "rgba(196, 195, 195, 1.00)"], "filename": "M026.JPG.jpe", "width": 816, "id": "240b168d69adbe1a578c0212cc0feff8", "height": 1054, "thumbnail": true}, "saison": "Summer / \u00c9t\u00e9", "english_name_nom_en_anglais": "Shield", "french_name_nom_francais": "L\u2019\u00c9cu de Sobieski", "annee": "1749", "dec": "-09:23:01.0", "dimension": "15,0'", "ra": "18:45:18.66"}, "record_timestamp": "2019-03-05T10:44:29.021+01:00"},{"datasetid": "catalogue-de-messier", "recordid": "0dcdd3c78b8558ce153231f09e86a53389222480", "fields": {"objet": "Galaxy / Galaxie", "const": "And", "mag": 8, "decouvreur": "Le Gentil", "ngc": "NGC 221", "image": "http://www.lasam.ca/messier/M032.JPG", "latin_name_nom_latin": "Andromeda", "messier": "M32", "image_url": {"mimetype": "image/jpeg", "format": "JPEG", "color_summary": ["rgba(222, 222, 222, 1.00)", "rgba(252, 252, 252, 1.00)", "rgba(249, 248, 248, 1.00)"], "filename": "M032.JPG.jpe", "width": 816, "id": "07dd9434047a7dedf82187c513b2eb3e", "height": 1054, "thumbnail": true}, "saison": "Autumn / Automne", "english_name_nom_en_anglais": "Andromeda", "french_name_nom_francais": "Androm\u00e8de", "annee": "1749", "dec": "+40:51:55.0", "dimension": "7,6' x 5,8'", "ra": "00:42:41.83"}, "record_timestamp": "2019-03-05T10:44:29.021+01:00"},{"datasetid": "catalogue-de-messier", "recordid": "30b961fe2cc39b412fcf46952b12677f3457200a", "fields": {"objet": "Open Cluster / Amas Ouvert", "const": "Aur", "mag": 6, "decouvreur": "Hodierna", "distance": 2750, "image": "http://www.lasam.ca/messier/M038.JPG", "ngc": "NGC 1912", "latin_name_nom_latin": "Auriga", "messier": "M38", "image_url": {"mimetype": "image/jpeg", "format": "JPEG", "color_summary": ["rgba(226, 225, 225, 1.00)", "rgba(207, 206, 207, 1.00)", "rgba(222, 221, 221, 1.00)"], "filename": "M038.JPG.jpe", "width": 816, "id": "483fc12f9290bcb0c244b5e65b774e54", "height": 1054, "thumbnail": true}, "saison": "Winter / Hiver", "english_name_nom_en_anglais": "Charioteer", "french_name_nom_francais": "Cocher", "annee": "1654", "dec": "+35:51:17.7", "dimension": "21,0'", "ra": "05:28:42.49"}, "record_timestamp": "2019-03-05T10:44:29.021+01:00"},{"datasetid": "catalogue-de-messier", "recordid": "4ec02d3de216100fcc434a46dfc7c2d8e429f8c1", "fields": {"objet": "Emission Nebula / N\u00e9buleuse \u00e0 \u00e9mission", "const": "Ori", "mag": 4, "decouvreur": "Peiresc", "distance": 1500, "image": "http://www.lasam.ca/messier/M042.JPG", "ngc": "NGC 9176", "latin_name_nom_latin": "Orion", "messier": "M42", "image_url": {"mimetype": "image/jpeg", "format": "JPEG", "color_summary": ["rgba(232, 231, 231, 1.00)", "rgba(250, 249, 249, 1.00)", "rgba(248, 248, 248, 1.00)"], "filename": "M042.JPG.jpe", "width": 816, "id": "90397cbe3746fedbf7f3fe98dd95c2f2", "height": 1054, "thumbnail": true}, "saison": "Winter / Hiver", "english_name_nom_en_anglais": "Orion, Hunter", "french_name_nom_francais": "Orion", "annee": "1610", "dec": "-05:23:22.8", "dimension": "30,0'", "ra": "05:35:16.48"}, "record_timestamp": "2019-03-05T10:44:29.021+01:00"},{"datasetid": "catalogue-de-messier", "recordid": "eaff5833bfb82f43a48e65c97151d0d3eb170790", "fields": {"objet": "Reflection Nebula / N\u00e9buleuse \u00e0 r\u00e9flexion", "const": "Ori", "mag": 9, "decouvreur": "Mairan", "distance": 1500, "image": "http://www.lasam.ca/messier/M043.JPG", "ngc": "NGC 1982", "latin_name_nom_latin": "Orion", "messier": "M43", "image_url": {"mimetype": "image/jpeg", "format": "JPEG", "color_summary": ["rgba(232, 231, 231, 1.00)", "rgba(250, 249, 249, 1.00)", "rgba(248, 248, 248, 1.00)"], "filename": "M043.JPG.jpe", "width": 816, "id": "b088495502b56818375fb970311cf4d1", "height": 1054, "thumbnail": true}, "saison": "Winter / Hiver", "english_name_nom_en_anglais": "Orion, Hunter", "french_name_nom_francais": "Orion", "annee": "1750", "dec": "-05:16:02.9", "dimension": "20,0' x 15,0'", "ra": "05:35:31.38"}, "record_timestamp": "2019-03-05T10:44:29.021+01:00"},{"datasetid": "catalogue-de-messier", "recordid": "4ac0891fc54ea74d4b8f122556931c5820c00478", "fields": {"objet": "Open Cluster / Amas Ouvert", "distance": 410, "image": "http://www.lasam.ca/messier/M045.JPG", "messier": "M45", "image_url": {"mimetype": "image/jpeg", "format": "JPEG", "color_summary": ["rgba(239, 238, 239, 1.00)", "rgba(251, 249, 250, 1.00)", "rgba(248, 248, 248, 1.00)"], "filename": "M045.JPG.jpe", "width": 816, "id": "3f56749618b208f4a29b63292151475e", "height": 1054, "thumbnail": true}, "saison": "Winter / Hiver", "mag": 1, "dimension": "120,0'"}, "record_timestamp": "2019-03-05T10:44:29.021+01:00"},{"datasetid": "catalogue-de-messier", "recordid": "28b51b1bde9ad3b74a9d733c6d821b86d2d78596", "fields": {"objet": "Open Cluster / Amas Ouvert", "const": "Cas", "mag": 6, "decouvreur": "Messier", "distance": 3000, "image": "http://www.lasam.ca/messier/M052.JPG", "ngc": "NGC 7654", "latin_name_nom_latin": "Cassiopeia", "messier": "M52", "image_url": {"mimetype": "image/jpeg", "format": "JPEG", "color_summary": ["rgba(241, 241, 242, 1.00)", "rgba(210, 209, 209, 1.00)", "rgba(202, 202, 202, 1.00)"], "filename": "M052.JPG.jpe", "width": 816, "id": "55c837dd2b2cb395ef59bddf713bc791", "height": 1054, "thumbnail": true}, "saison": "Autumn / Automne", "english_name_nom_en_anglais": "Cassiopeia", "french_name_nom_francais": "Cassiop\u00e9e", "annee": "1774", "dec": "+61:35:35.4", "dimension": "13,0'", "ra": "23:24:48.40"}, "record_timestamp": "2019-03-05T10:44:29.021+01:00"},{"datasetid": "catalogue-de-messier", "recordid": "de85fd4bf4ba6c585ce7a526753e51dade84c6c2", "fields": {"objet": "Globular Cluster / Amas Globulaire", "const": "Com", "mag": 7, "decouvreur": "Bode", "distance": 69000, "image": "http://www.lasam.ca/messier/M053.JPG", "ngc": "NGC 5024", "latin_name_nom_latin": "Coma Berenices", "messier": "M53", "image_url": {"mimetype": "image/jpeg", "format": "JPEG", "color_summary": ["rgba(242, 241, 241, 1.00)", "rgba(253, 252, 252, 1.00)", "rgba(249, 249, 249, 1.00)"], "filename": "M053.JPG.jpe", "width": 816, "id": "4a1d56b7713c16cbe97e397d9b2aee83", "height": 1054, "thumbnail": true}, "saison": "Spring / Printemps", "english_name_nom_en_anglais": "Hair of Berenice", "french_name_nom_francais": "Chevelure de B\u00e9r\u00e9nice", "annee": "1775", "dec": "+18:10:08.8", "dimension": "14,4'", "ra": "13:12:55.23"}, "record_timestamp": "2019-03-05T10:44:29.021+01:00"},{"datasetid": "catalogue-de-messier", "recordid": "29d04f1e87ccf3c9e5a843b7da6edbefb3af1e71", "fields": {"objet": "Globular Cluster / Amas Globulaire", "const": "Sgr", "mag": 7, "decouvreur": "Lacaille", "distance": 20000, "image": "http://www.lasam.ca/messier/M055.JPG", "ngc": "NGC 6809", "latin_name_nom_latin": "Sagittarius", "messier": "M55", "image_url": {"mimetype": "image/jpeg", "format": "JPEG", "color_summary": ["rgba(226, 225, 225, 1.00)", "rgba(245, 244, 244, 1.00)", "rgba(249, 248, 248, 1.00)"], "filename": "M055.JPG.jpe", "width": 816, "id": "fdf05919dcf9a0e97cd120ae69f6db83", "height": 1054, "thumbnail": true}, "saison": "Summer / \u00c9t\u00e9", "english_name_nom_en_anglais": "Archer", "french_name_nom_francais": "Sagittaire", "annee": "1751", "dec": "-30:57:43.5", "dimension": "14,8'", "ra": "19:39:59.40"}, "record_timestamp": "2019-03-05T10:44:29.021+01:00"},{"datasetid": "catalogue-de-messier", "recordid": "72ceba7f9ed12c0c02180c086e4b98af5c869b90", "fields": {"objet": "Galaxy / Galaxie", "const": "Vir", "mag": 9, "decouvreur": "Messier", "distance": 41000000, "image": "http://www.lasam.ca/messier/M058.JPG", "ngc": "NGC 4579", "latin_name_nom_latin": "Virgo", "messier": "M58", "image_url": {"mimetype": "image/jpeg", "format": "JPEG", "color_summary": ["rgba(241, 240, 240, 1.00)", "rgba(252, 251, 251, 1.00)", "rgba(249, 248, 248, 1.00)"], "filename": "M058.JPG.jpe", "width": 816, "id": "fdae19a169fcd3dd1df72a00a8ca29ff", "height": 1054, "thumbnail": true}, "saison": "Spring / Printemps", "english_name_nom_en_anglais": "Virgin", "french_name_nom_francais": "Vierge", "annee": "1779", "dec": "+11:49:05.5", "dimension": "5,4' x 4,4'", "ra": "12:37:43.52"}, "record_timestamp": "2019-03-05T10:44:29.021+01:00"},{"datasetid": "catalogue-de-messier", "recordid": "f9ca8dcf4e7d122f9831f178eafa8d70ef91572f", "fields": {"objet": "Galaxy / Galaxie", "const": "Vir", "mag": 8, "decouvreur": "Koehler", "distance": 41000000, "image": "http://www.lasam.ca/messier/M060.JPG", "ngc": "NGC 4649", "latin_name_nom_latin": "Virgo", "messier": "M60", "image_url": {"mimetype": "image/jpeg", "format": "JPEG", "color_summary": ["rgba(241, 240, 240, 1.00)", "rgba(252, 251, 251, 1.00)", "rgba(249, 248, 249, 1.00)"], "filename": "M060.JPG.jpe", "width": 816, "id": "f3eb52d394d6faf0a835a793b13a4925", "height": 1054, "thumbnail": true}, "saison": "Spring / Printemps", "english_name_nom_en_anglais": "Virgin", "french_name_nom_francais": "Vierge", "annee": "1779", "dec": "+11:33:09.7", "dimension": "7,2' x 6,2'", "ra": "12:43:39.98"}, "record_timestamp": "2019-03-05T10:44:29.021+01:00"},{"datasetid": "catalogue-de-messier", "recordid": "89670f7e191f09c2c610a8ca53fd6a6e673d8cf0", "fields": {"objet": "Globular Cluster / Amas Globulaire", "const": "Hya", "mag": 8, "decouvreur": "M\u00e9chain", "distance": 36000, "image": "http://www.lasam.ca/messier/M068.JPG", "ngc": "NGC 4590", "latin_name_nom_latin": "Hydra", "messier": "M68", "image_url": {"mimetype": "image/jpeg", "format": "JPEG", "color_summary": ["rgba(241, 240, 240, 1.00)", "rgba(253, 253, 253, 1.00)", "rgba(251, 251, 251, 1.00)"], "filename": "M068.JPG.jpe", "width": 816, "id": "463c07501631673232605106f7fae95f", "height": 1054, "thumbnail": true}, "saison": "Spring / Printemps", "english_name_nom_en_anglais": "Hydra, Sea Snake", "french_name_nom_francais": "Hydre", "annee": "1780", "dec": "-26:44:34.9", "dimension": "9,8'", "ra": "12:39:28.01"}, "record_timestamp": "2019-03-05T10:44:29.021+01:00"},{"datasetid": "catalogue-de-messier", "recordid": "d47a40e343ae0021eaefc8140b31de7646260e33", "fields": {"objet": "Galaxy / Galaxie", "const": "Hya", "mag": 7, "decouvreur": "Lacaille", "distance": 8500000, "image": "http://www.lasam.ca/messier/M083.JPG", "ngc": "NGC 5236", "latin_name_nom_latin": "Hydra", "messier": "M83", "image_url": {"mimetype": "image/jpeg", "format": "JPEG", "color_summary": ["rgba(241, 241, 241, 1.00)", "rgba(253, 252, 252, 1.00)", "rgba(249, 249, 249, 1.00)"], "filename": "M083.JPG.jpe", "width": 816, "id": "d1a983cfd6854a987f370d22aa518c60", "height": 1054, "thumbnail": true}, "saison": "Spring / Printemps", "english_name_nom_en_anglais": "Hydra, Sea Snake", "french_name_nom_francais": "Hydre", "annee": "1751", "dec": "-29:51:55.5", "dimension": "11,0' x 10,0'", "ra": "13:37:00.95"}, "record_timestamp": "2019-03-05T10:44:29.021+01:00"},{"datasetid": "catalogue-de-messier", "recordid": "0e3e6ef88b90fda5d93874323da9cc4a30af3648", "fields": {"objet": "Galaxy / Galaxie", "const": "Vir", "mag": 9, "decouvreur": "Messier", "distance": 20000000, "image": "http://www.lasam.ca/messier/M086.JPG", "ngc": "NGC 4406", "latin_name_nom_latin": "Virgo", "messier": "M86", "image_url": {"mimetype": "image/jpeg", "format": "JPEG", "color_summary": ["rgba(241, 240, 240, 1.00)", "rgba(252, 251, 251, 1.00)", "rgba(249, 248, 248, 1.00)"], "filename": "M086.JPG.jpe", "width": 816, "id": "27df2430c095f56f65f63bbb304b032e", "height": 1054, "thumbnail": true}, "saison": "Spring / Printemps", "english_name_nom_en_anglais": "Virgin", "french_name_nom_francais": "Vierge", "annee": "1781", "dec": "+12:56:46.4", "dimension": "7,4' x 5,5'", "ra": "12:26:11.74"}, "record_timestamp": "2019-03-05T10:44:29.021+01:00"},{"datasetid": "catalogue-de-messier", "recordid": "4d0bdba81ca8120092e5cfd5e5c58bf22347c51f", "fields": {"objet": "Open Cluster / Amas Ouvert", "const": "Pup", "mag": 4, "decouvreur": "Hodierna", "distance": 1750, "image": "http://www.lasam.ca/messier/M047.JPG", "ngc": "NGC 2422", "latin_name_nom_latin": "Puppis", "messier": "M47", "image_url": {"mimetype": "image/jpeg", "format": "JPEG", "color_summary": ["rgba(214, 214, 214, 1.00)", "rgba(215, 214, 214, 1.00)", "rgba(213, 212, 212, 1.00)"], "filename": "M047.JPG.jpe", "width": 816, "id": "095f19d850f27140faf38bb6f75d0d1c", "height": 1054, "thumbnail": true}, "saison": "Winter / Hiver", "english_name_nom_en_anglais": "Stern,Poop deck", "french_name_nom_francais": "Poupe", "annee": "1654", "dec": "-14:28:57.4", "dimension": "22,0'", "ra": "07:36:35.02"}, "record_timestamp": "2019-03-05T10:44:29.021+01:00"},{"datasetid": "catalogue-de-messier", "recordid": "38f137fc167903f4ac3024776d0e91a7bab5e3bf", "fields": {"objet": "Galaxy / Galaxie", "const": "Leo", "mag": 9, "decouvreur": "M\u00e9chain", "distance": 29000000, "image": "http://www.lasam.ca/messier/M065.JPG", "ngc": "NGC 3623", "latin_name_nom_latin": "Leo", "messier": "M65", "image_url": {"mimetype": "image/jpeg", "format": "JPEG", "color_summary": ["rgba(242, 241, 241, 1.00)", "rgba(251, 251, 251, 1.00)", "rgba(250, 249, 249, 1.00)"], "filename": "M065.JPG.jpe", "width": 816, "id": "0da15d5d0bb1bb0c0d3a876bcf6cebc0", "height": 1054, "thumbnail": true}, "saison": "Spring / Printemps", "english_name_nom_en_anglais": "Lion", "french_name_nom_francais": "Lion", "annee": "1780", "dec": "+13:05:32.5", "dimension": "10,0' x 3,3'", "ra": "11:18:55.92"}, "record_timestamp": "2019-03-05T10:44:29.021+01:00"},{"datasetid": "catalogue-de-messier", "recordid": "f987515dadff6877b63134e571d146a85847cbaa", "fields": {"objet": "Globular Cluster / Amas Globulaire", "const": "Lep", "mag": 8, "decouvreur": "M\u00e9chain", "distance": 43400, "image": "http://www.lasam.ca/messier/M079.JPG", "ngc": "NGC 1904", "latin_name_nom_latin": "Lepus", "messier": "M79", "image_url": {"mimetype": "image/jpeg", "format": "JPEG", "color_summary": ["rgba(239, 239, 239, 1.00)", "rgba(253, 252, 252, 1.00)", "rgba(250, 249, 249, 1.00)"], "filename": "M079.JPG.jpe", "width": 816, "id": "4f70401504999a3f173169f160b545f3", "height": 1054, "thumbnail": true}, "saison": "Winter / Hiver", "english_name_nom_en_anglais": "Hare", "french_name_nom_francais": "Li\u00e8vre", "annee": "1780", "dec": "-24:31:27.2", "dimension": "7,8'", "ra": "05:24:10.59"}, "record_timestamp": "2019-03-05T10:44:29.021+01:00"},{"datasetid": "catalogue-de-messier", "recordid": "cbdfffff3c6570c796121bc90dd6976c75b98462", "fields": {"objet": "Galaxy / Galaxie", "const": "Vir", "mag": 9, "decouvreur": "Messier", "distance": 41000000, "image": "http://www.lasam.ca/messier/M084.JPG", "ngc": "NGC 4374", "latin_name_nom_latin": "Virgo", "messier": "M84", "image_url": {"mimetype": "image/jpeg", "format": "JPEG", "color_summary": ["rgba(241, 240, 241, 1.00)", "rgba(252, 251, 251, 1.00)", "rgba(249, 248, 248, 1.00)"], "filename": "M084.JPG.jpe", "width": 816, "id": "5338a7e027e132bbb2c7e00b94249fa9", "height": 1054, "thumbnail": true}, "saison": "Spring / Printemps", "english_name_nom_en_anglais": "Virgin", "french_name_nom_francais": "Vierge", "annee": "1781", "dec": "+12:53:13.1", "dimension": "5,0' x 4,4'", "ra": "12:25:03.74"}, "record_timestamp": "2019-03-05T10:44:29.021+01:00"},{"datasetid": "catalogue-de-messier", "recordid": "5fbe44fdf5659dc5f3b6616879ae2827fa785c74", "fields": {"objet": "Emission Nebula / N\u00e9buleuse \u00e0 \u00e9mission", "const": "Sgr", "mag": 6, "decouvreur": "Le Gentil", "distance": 2300, "image": "http://www.lasam.ca/messier/M020.JPG", "ngc": "NGC 6514", "latin_name_nom_latin": "Sagittarius", "messier": "M20", "image_url": {"mimetype": "image/jpeg", "format": "JPEG", "color_summary": ["rgba(213, 211, 212, 1.00)", "rgba(188, 186, 187, 1.00)", "rgba(185, 184, 184, 1.00)"], "filename": "M020.JPG.jpe", "width": 816, "id": "78c02c7247e4b158d47d911995fa498b", "height": 1054, "thumbnail": true}, "saison": "Summer / \u00c9t\u00e9", "english_name_nom_en_anglais": "Archer", "french_name_nom_francais": "Sagittaire", "annee": "1749", "dec": "-22:58:18.8", "dimension": "29,0' x 27,0'", "ra": "18:02:42.11"}, "record_timestamp": "2019-03-05T10:44:29.021+01:00"},{"datasetid": "catalogue-de-messier", "recordid": "049bf2f3452e44ff4549ef97559eaabe4235fb7c", "fields": {"objet": "Globular Cluster / Amas Globulaire", "const": "Oph", "mag": 6, "decouvreur": "Messier", "distance": 16300, "image": "http://www.lasam.ca/messier/M010.JPG", "ngc": "NGC 6254", "latin_name_nom_latin": "Ophiuchus", "messier": "M10", "image_url": {"mimetype": "image/jpeg", "format": "JPEG", "color_summary": ["rgba(240, 240, 240, 1.00)", "rgba(254, 254, 254, 1.00)", "rgba(232, 232, 232, 1.00)"], "filename": "M010.JPG.jpe", "width": 816, "id": "dc53b1bdbeaec70be1cfffe6a8ddb11e", "height": 1054, "thumbnail": true}, "saison": "Summer / \u00c9t\u00e9", "english_name_nom_en_anglais": "Serpent Holder", "french_name_nom_francais": "Ophiuchus", "annee": "1764", "dec": "-04:05:57.6", "dimension": "12,2'", "ra": "16:57:08.99"}, "record_timestamp": "2019-03-05T10:44:29.021+01:00"},{"datasetid": "catalogue-de-messier", "recordid": "6cc91740187da27131e8922a12a50aa44add9f8c", "fields": {"objet": "Globular Cluster / Amas Globulaire", "const": "Oph", "mag": 7, "decouvreur": "Messier", "distance": 24000, "image": "http://www.lasam.ca/messier/M014.JPG", "ngc": "NGC 6402", "latin_name_nom_latin": "Ophiuchus", "messier": "M14", "image_url": {"mimetype": "image/jpeg", "format": "JPEG", "color_summary": ["rgba(232, 232, 232, 1.00)", "rgba(251, 251, 251, 1.00)", "rgba(225, 224, 225, 1.00)"], "filename": "M014.JPG.jpe", "width": 816, "id": "d8d2764b73ed02dbff8168ea88e50b74", "height": 1054, "thumbnail": true}, "saison": "Summer / \u00c9t\u00e9", "english_name_nom_en_anglais": "Serpent Holder", "french_name_nom_francais": "Ophiuchus", "annee": "1764", "dec": "-03:14:45.3", "dimension": "6,7'", "ra": "17:37:36.16"}, "record_timestamp": "2019-03-05T10:44:29.021+01:00"},{"datasetid": "catalogue-de-messier", "recordid": "8216d7c80e624c25037eddfd57b5d49963bc2f4b", "fields": {"objet": "Open Cluster / Amas Ouvert", "const": "Sgr", "mag": 11, "decouvreur": "Messier", "distance": 16000, "image": "http://www.lasam.ca/messier/M024.JPG", "ngc": "NGC 6603", "latin_name_nom_latin": "Sagittarius", "messier": "M24", "image_url": {"mimetype": "image/jpeg", "format": "JPEG", "color_summary": ["rgba(220, 219, 219, 1.00)", "rgba(197, 196, 196, 1.00)", "rgba(183, 182, 183, 1.00)"], "filename": "M024.JPG.jpe", "width": 816, "id": "dd4a0f4bd2108422bb8abb2fb6c453f7", "height": 1054, "thumbnail": true}, "saison": "Summer / \u00c9t\u00e9", "english_name_nom_en_anglais": "Archer", "french_name_nom_francais": "Sagittaire", "annee": "1764", "dec": "-18:30:52.4", "dimension": "45,0'", "ra": "18:16:56.12"}, "record_timestamp": "2019-03-05T10:44:29.021+01:00"},{"datasetid": "catalogue-de-messier", "recordid": "70029ae1ed26cdddc0b042eb424b24eb69b353ce", "fields": {"objet": "Galaxy / Galaxie", "const": "Tri", "mag": 5, "decouvreur": "Messier", "distance": 2723000, "image": "http://www.lasam.ca/messier/M033.JPG", "ngc": "NGC 598", "latin_name_nom_latin": "Triangulum", "messier": "M33", "image_url": {"mimetype": "image/jpeg", "format": "JPEG", "color_summary": ["rgba(239, 238, 238, 1.00)", "rgba(252, 252, 252, 1.00)", "rgba(250, 249, 249, 1.00)"], "filename": "M033.JPG.jpe", "width": 816, "id": "69d661776ffd8a5b3cfdd819f0455a22", "height": 1054, "thumbnail": true}, "saison": "Autumn / Automne", "english_name_nom_en_anglais": "Triangle", "french_name_nom_francais": "Triangle", "annee": "1764", "dec": "+30:39:36.8", "dimension": "62,0. x 39,0'", "ra": "01:33:50.89"}, "record_timestamp": "2019-03-05T10:44:29.021+01:00"},{"datasetid": "catalogue-de-messier", "recordid": "7e4c1cf3b2a46e7fcf200836458e22dea835a247", "fields": {"objet": "Galaxy / Galaxie", "const": "Com", "mag": 10, "decouvreur": "Messier", "distance": 37000000, "image": "http://www.lasam.ca/messier/M091.JPG", "ngc": "NGC 4548", "latin_name_nom_latin": "Coma Berenices", "messier": "M91", "image_url": {"mimetype": "image/jpeg", "format": "JPEG", "color_summary": ["rgba(241, 241, 241, 1.00)", "rgba(252, 251, 251, 1.00)", "rgba(249, 248, 248, 1.00)"], "filename": "M091.JPG.jpe", "width": 816, "id": "284c5bc7c93f0088d9a250d0e946c902", "height": 1054, "thumbnail": true}, "saison": "Spring / Printemps", "english_name_nom_en_anglais": "Hair of Berenice", "french_name_nom_francais": "Chevelure de B\u00e9r\u00e9nice", "annee": "1781", "dec": "+14:29:46.8", "dimension": "5,4' x 4,4'", "ra": "12:35:26.45"}, "record_timestamp": "2019-03-05T10:44:29.021+01:00"},{"datasetid": "catalogue-de-messier", "recordid": "6fb430b817b86b37240f8f318192f462c6eeb56b", "fields": {"objet": "Globular Cluster / Amas Globulaire", "const": "Sgr", "mag": 8, "decouvreur": "M\u00e9chain", "distance": 78500, "image": "http://www.lasam.ca/messier/M075.JPG", "ngc": "NGC 6864", "latin_name_nom_latin": "Sagittarius", "messier": "M75", "image_url": {"mimetype": "image/jpeg", "format": "JPEG", "color_summary": ["rgba(236, 235, 235, 1.00)", "rgba(251, 250, 250, 1.00)", "rgba(251, 250, 250, 1.00)"], "filename": "M075.JPG.jpe", "width": 816, "id": "00f582867eec79eab3bc4d51021d8178", "height": 1054, "thumbnail": true}, "saison": "Summer / \u00c9t\u00e9", "english_name_nom_en_anglais": "Archer", "french_name_nom_francais": "Sagittaire", "annee": "1780", "dec": "-21:55:20.0", "dimension": "4,6'", "ra": "20:06:04.84"}, "record_timestamp": "2019-03-05T10:44:29.021+01:00"},{"datasetid": "catalogue-de-messier", "recordid": "97dca12c94a942e4a705d385b3789f7b413cbcde", "fields": {"objet": "Galaxy / Galaxie", "const": "Leo", "mag": 9, "decouvreur": "M\u00e9chain", "distance": 20300000, "image": "http://www.lasam.ca/messier/M095.JPG", "ngc": "NGC 3351", "latin_name_nom_latin": "Leo", "messier": "M95", "image_url": {"mimetype": "image/jpeg", "format": "JPEG", "color_summary": ["rgba(241, 240, 240, 1.00)", "rgba(251, 251, 251, 1.00)", "rgba(250, 250, 250, 1.00)"], "filename": "M095.JPG.jpe", "width": 816, "id": "d78c022080defa2df511b4a74951c911", "height": 1054, "thumbnail": true}, "saison": "Spring / Printemps", "english_name_nom_en_anglais": "Lion", "french_name_nom_francais": "Lion", "annee": "1781", "dec": "+11:42:13.7", "dimension": "7,4' x 5,1'", "ra": "10:43:57.70"}, "record_timestamp": "2019-03-05T10:44:29.021+01:00"},{"datasetid": "catalogue-de-messier", "recordid": "fb83e2388fa0677bdd7a888bbab2bf6c60339aba", "fields": {"objet": "Open Cluster / Amas Ouvert", "const": "CMa", "mag": 4, "decouvreur": "Hodierna", "distance": 1600, "image": "http://www.lasam.ca/messier/M041.JPG", "ngc": "NGC 2287", "latin_name_nom_latin": "Canis Major", "messier": "M41", "image_url": {"mimetype": "image/jpeg", "format": "JPEG", "color_summary": ["rgba(217, 217, 217, 1.00)", "rgba(241, 240, 240, 1.00)", "rgba(249, 248, 248, 1.00)"], "filename": "M041.JPG.jpe", "width": 816, "id": "29f4c224d82abed7818f5b0d8d2c88f2", "height": 1054, "thumbnail": true}, "saison": "Winter / Hiver", "english_name_nom_en_anglais": "Great Dog", "french_name_nom_francais": "Grand Chien", "annee": "1654", "dec": "-20:45:15.2", "dimension": "30,0'", "ra": "06:45:59.94"}, "record_timestamp": "2019-03-05T10:44:29.021+01:00"},{"datasetid": "catalogue-de-messier", "recordid": "6c60248c08580e6b00fbd15fc64b678bcb554518", "fields": {"objet": "Open Cluster / Amas Ouvert", "const": "Pup", "mag": 6, "decouvreur": "Messier", "distance": 3200, "image": "http://www.lasam.ca/messier/M046.JPG", "ngc": "NGC 2437", "latin_name_nom_latin": "Puppis", "messier": "M46", "image_url": {"mimetype": "image/jpeg", "format": "JPEG", "color_summary": ["rgba(216, 216, 216, 1.00)", "rgba(215, 214, 214, 1.00)", "rgba(210, 210, 210, 1.00)"], "filename": "M046.JPG.jpe", "width": 816, "id": "b01e8f5ad9db9482252f14ccd3313cd9", "height": 1054, "thumbnail": true}, "saison": "Winter / Hiver", "english_name_nom_en_anglais": "Stern,Poop deck", "french_name_nom_francais": "Poupe", "annee": "1771", "dec": "-14:48:36.0", "dimension": "24,0'", "ra": "07:41:46.82"}, "record_timestamp": "2019-03-05T10:44:29.021+01:00"},{"datasetid": "catalogue-de-messier", "recordid": "f7e5591290b9e9b7cf126919a8d2b12faabbcee6", "fields": {"objet": "Galaxy / Galaxie", "const": "Vir", "mag": 9, "decouvreur": "Koehler", "distance": 41000000, "image": "http://www.lasam.ca/messier/M059.JPG", "ngc": "NGC 4621", "latin_name_nom_latin": "Virgo", "messier": "M59", "image_url": {"mimetype": "image/jpeg", "format": "JPEG", "color_summary": ["rgba(241, 240, 240, 1.00)", "rgba(252, 251, 251, 1.00)", "rgba(249, 248, 249, 1.00)"], "filename": "M059.JPG.jpe", "width": 816, "id": "b24a84de6da3360d826cf5c3ab0261d1", "height": 1054, "thumbnail": true}, "saison": "Spring / Printemps", "english_name_nom_en_anglais": "Virgin", "french_name_nom_francais": "Vierge", "annee": "1779", "dec": "+11:38:49.3", "dimension": "5,1' x 3,4'", "ra": "12:42:02.24"}, "record_timestamp": "2019-03-05T10:44:29.021+01:00"},{"datasetid": "catalogue-de-messier", "recordid": "b93b06165946877ab2d01c5fbf7b15f4c9765eb0", "fields": {"objet": "Galaxy / Galaxie", "const": "Vir", "mag": 8, "decouvreur": "Messier", "distance": 41000000, "image": "http://www.lasam.ca/messier/M049.JPG", "ngc": "NGC 4472", "latin_name_nom_latin": "Virgo", "messier": "M49", "image_url": {"mimetype": "image/jpeg", "format": "JPEG", "color_summary": ["rgba(241, 240, 240, 1.00)", "rgba(252, 251, 251, 1.00)", "rgba(249, 248, 248, 1.00)"], "filename": "M049.JPG.jpe", "width": 816, "id": "25046a4043828d3b133a4a98e981ae82", "height": 1054, "thumbnail": true}, "saison": "Spring / Printemps", "english_name_nom_en_anglais": "Virgin", "french_name_nom_francais": "Vierge", "annee": "1771", "dec": "+08:00:01.7", "dimension": "8,9' x 7,4'", "ra": "12:29:46.76"}, "record_timestamp": "2019-03-05T10:44:29.021+01:00"},{"datasetid": "catalogue-de-messier", "recordid": "0a4d6e998446e99fd6e6e90401a8e2ce825a064b", "fields": {"objet": "Galaxy / Galaxie", "const": "Com", "mag": 9, "decouvreur": "M\u00e9chain", "distance": 41000000, "image": "http://www.lasam.ca/messier/M099.JPG", "ngc": "NGC 4254", "latin_name_nom_latin": "Coma Berenices", "messier": "M99", "image_url": {"mimetype": "image/jpeg", "format": "JPEG", "color_summary": ["rgba(242, 241, 241, 1.00)", "rgba(252, 251, 251, 1.00)", "rgba(248, 248, 248, 1.00)"], "filename": "M099.JPG.jpe", "width": 816, "id": "76a67bc41ee3e41b25567e06b20bab39", "height": 1054, "thumbnail": true}, "saison": "Spring / Printemps", "english_name_nom_en_anglais": "Hair of Berenice", "french_name_nom_francais": "Chevelure de B\u00e9r\u00e9nice", "annee": "1781", "dec": "+14:24:59.4", "dimension": "5,4' x 4,8'", "ra": "12:18:49.60"}, "record_timestamp": "2019-03-05T10:44:29.021+01:00"},{"datasetid": "catalogue-de-messier", "recordid": "541f12b0672cd4f6a9887cccecdcbc3aa381fb34", "fields": {"objet": "Emission Nebula / N\u00e9buleuse \u00e0 \u00e9mission", "const": "Sgr", "mag": 5, "decouvreur": "Flamsteed", "distance": 4850, "image": "http://www.lasam.ca/messier/M008.JPG", "ngc": "NGC 6523", "latin_name_nom_latin": "Sagittarius", "messier": "M8", "image_url": {"mimetype": "image/jpeg", "format": "JPEG", "color_summary": ["rgba(206, 204, 204, 1.00)", "rgba(186, 185, 186, 1.00)", "rgba(186, 185, 185, 1.00)"], "filename": "M008.JPG.jpe", "width": 816, "id": "0a09915c6203f288d82ddb1236a986a1", "height": 1054, "thumbnail": true}, "saison": "Summer / \u00c9t\u00e9", "english_name_nom_en_anglais": "Archer", "french_name_nom_francais": "Sagittaire", "annee": "1680", "dec": "-24:22:48.6", "dimension": "90,0' x 40,0'", "ra": "18:03:41.27"}, "record_timestamp": "2019-03-05T10:44:29.021+01:00"},{"datasetid": "catalogue-de-messier", "recordid": "5c20f3a7ed2c2ccdf8610308eedd414e782aded8", "fields": {"objet": "Open Cluster / Amas Ouvert", "const": "Sct", "mag": 5, "decouvreur": "Kirch", "distance": 5600, "image": "http://www.lasam.ca/messier/M011.JPG", "ngc": "NGC 6705", "latin_name_nom_latin": "Scutum", "messier": "M11", "image_url": {"mimetype": "image/jpeg", "format": "JPEG", "color_summary": ["rgba(202, 202, 202, 1.00)", "rgba(215, 214, 215, 1.00)", "rgba(199, 198, 198, 1.00)"], "filename": "M011.JPG.jpe", "width": 816, "id": "4bc62585d114ad1c0fc3075fcf93c6e5", "height": 1054, "thumbnail": true}, "saison": "Summer / \u00c9t\u00e9", "english_name_nom_en_anglais": "Shield", "french_name_nom_francais": "L\u2019\u00c9cu de Sobieski", "annee": "1681", "dec": "-06:16:12.1", "dimension": "14,0'", "ra": "18:51:05.99"}, "record_timestamp": "2019-03-05T10:44:29.021+01:00"},{"datasetid": "catalogue-de-messier", "recordid": "669d15b09eb016ae8916cb427e633744ad3604f1", "fields": {"objet": "Open Cluster / Amas Ouvert", "const": "Sgr", "mag": 5, "decouvreur": "Messier", "distance": 2150, "image": "http://www.lasam.ca/messier/M023.JPG", "ngc": "NGC 6494", "latin_name_nom_latin": "Sagittarius", "messier": "M23", "image_url": {"mimetype": "image/jpeg", "format": "JPEG", "color_summary": ["rgba(232, 231, 231, 1.00)", "rgba(197, 196, 196, 1.00)", "rgba(182, 181, 182, 1.00)"], "filename": "M023.JPG.jpe", "width": 816, "id": "ff119a9dfc69d428705050aa76dbb11a", "height": 1054, "thumbnail": true}, "saison": "Summer / \u00c9t\u00e9", "english_name_nom_en_anglais": "Archer", "french_name_nom_francais": "Sagittaire", "annee": "1764", "dec": "-18:59:07.2", "dimension": "25,0'", "ra": "17:57:04.77"}, "record_timestamp": "2019-03-05T10:44:29.021+01:00"},{"datasetid": "catalogue-de-messier", "recordid": "b70a8f1742eb9e93924fbab9d7d3c43d926d2b19", "fields": {"objet": "Open Cluster / Amas Ouvert", "const": "Sgr", "mag": 4, "decouvreur": "Ch\u00e9seaux", "distance": 2060, "image": "http://www.lasam.ca/messier/M025.JPG", "ngc": "IC4725", "latin_name_nom_latin": "Sagittarius", "messier": "M25", "image_url": {"mimetype": "image/jpeg", "format": "JPEG", "color_summary": ["rgba(209, 208, 209, 1.00)", "rgba(196, 194, 194, 1.00)", "rgba(190, 188, 189, 1.00)"], "filename": "M025.JPG.jpe", "width": 816, "id": "c18a9c95c4de885305003df09bc0b129", "height": 1054, "thumbnail": true}, "saison": "Summer / \u00c9t\u00e9", "english_name_nom_en_anglais": "Archer", "french_name_nom_francais": "Sagittaire", "annee": "1746", "dec": "-19:06:53.8", "dimension": "35,0'", "ra": "18:31:46.77"}, "record_timestamp": "2019-03-05T10:44:29.021+01:00"},{"datasetid": "catalogue-de-messier", "recordid": "360820525445f8b820bfe076a85c620c061733a5", "fields": {"objet": "Globular Cluster / Amas Globulaire", "const": "Sgr", "mag": 7, "decouvreur": "Messier", "distance": 49000, "image": "http://www.lasam.ca/messier/M054.JPG", "ngc": "NGC 6715", "latin_name_nom_latin": "Sagittarius", "messier": "M54", "image_url": {"mimetype": "image/jpeg", "format": "JPEG", "color_summary": ["rgba(194, 193, 193, 1.00)", "rgba(210, 209, 209, 1.00)", "rgba(228, 227, 227, 1.00)"], "filename": "M054.JPG.jpe", "width": 816, "id": "8b3604c4ff6814a981af8cbd38c607ee", "height": 1054, "thumbnail": true}, "saison": "Summer / \u00c9t\u00e9", "english_name_nom_en_anglais": "Archer", "french_name_nom_francais": "Sagittaire", "annee": "1778", "dec": "-30:28:42.6", "dimension": "5,5'", "ra": "18:55:03.27"}, "record_timestamp": "2019-03-05T10:44:29.021+01:00"},{"datasetid": "catalogue-de-messier", "recordid": "84c799723cfa16d28e1448c98440e66f9f0a7c84", "fields": {"objet": "Globular Cluster / Amas Globulaire", "const": "Oph", "mag": 6, "decouvreur": "Messier", "distance": 22500, "image": "http://www.lasam.ca/messier/M062.JPG", "ngc": "NGC 6266", "latin_name_nom_latin": "Ophiuchus", "messier": "M62", "image_url": {"mimetype": "image/jpeg", "format": "JPEG", "color_summary": ["rgba(203, 202, 203, 1.00)", "rgba(204, 203, 204, 1.00)", "rgba(200, 200, 200, 1.00)"], "filename": "M062.JPG.jpe", "width": 816, "id": "d06bc159284f4078fd9134d9577bc700", "height": 1054, "thumbnail": true}, "saison": "Summer / \u00c9t\u00e9", "english_name_nom_en_anglais": "Serpent Holder", "french_name_nom_francais": "Ophiuchus", "annee": "1771", "dec": "-30:06:44.5", "dimension": "6,3'", "ra": "17:01:12.60"}, "record_timestamp": "2019-03-05T10:44:29.021+01:00"},{"datasetid": "catalogue-de-messier", "recordid": "b5ca90dbb48a4c05232d6c46c95ae97bb370451a", "fields": {"objet": "Galaxy / Galaxie", "const": "Com", "mag": 8, "decouvreur": "Bode", "distance": 11800000, "image": "http://www.lasam.ca/messier/M064.JPG", "ngc": "NGC 4826", "latin_name_nom_latin": "Coma Berenices", "messier": "M64", "image_url": {"mimetype": "image/jpeg", "format": "JPEG", "color_summary": ["rgba(242, 241, 241, 1.00)", "rgba(253, 252, 252, 1.00)", "rgba(249, 248, 248, 1.00)"], "filename": "M064.JPG.jpe", "width": 816, "id": "96e7c96295c70aeecae2bb112aa7783e", "height": 1054, "thumbnail": true}, "saison": "Spring / Printemps", "english_name_nom_en_anglais": "Hair of Berenice", "french_name_nom_francais": "Chevelure de B\u00e9r\u00e9nice", "annee": "1775", "dec": "+21:40:58.7", "dimension": "9,3' x 5,4'", "ra": "12:56:43.64"}, "record_timestamp": "2019-03-05T10:44:29.021+01:00"},{"datasetid": "catalogue-de-messier", "recordid": "aa7a42303eb3ad184038c4f943f04e584287c62b", "fields": {"objet": "Open Cluster / Amas Ouvert", "const": "Cnc", "mag": 6, "decouvreur": "Koehler", "distance": 2600, "image": "http://www.lasam.ca/messier/M067.JPG", "ngc": "NGC 2682", "latin_name_nom_latin": "Cancer", "messier": "M67", "image_url": {"mimetype": "image/jpeg", "format": "JPEG", "color_summary": ["rgba(239, 238, 238, 1.00)", "rgba(252, 251, 251, 1.00)", "rgba(250, 250, 250, 1.00)"], "filename": "M067.JPG.jpe", "width": 816, "id": "58e4e9e693132bcfabbbfdb507939897", "height": 1054, "thumbnail": true}, "saison": "Spring / Printemps", "english_name_nom_en_anglais": "Crab", "french_name_nom_francais": "Cancer", "annee": "1778", "dec": "+11:48:43.0", "dimension": "27,0'", "ra": "08:51:20.13"}, "record_timestamp": "2019-03-05T10:44:29.021+01:00"},{"datasetid": "catalogue-de-messier", "recordid": "a9f07a5cd5013bdc68b040686e71e4b14d9dc2a0", "fields": {"objet": "Globular Cluster / Amas Globulaire", "const": "Sge", "mag": 8, "decouvreur": "Ch\u00e9seaux", "distance": 13000, "image": "http://www.lasam.ca/messier/M071.JPG", "ngc": "NGC 6838", "latin_name_nom_latin": "Sagitta", "messier": "M71", "image_url": {"mimetype": "image/jpeg", "format": "JPEG", "color_summary": ["rgba(194, 193, 193, 1.00)", "rgba(217, 216, 216, 1.00)", "rgba(220, 220, 220, 1.00)"], "filename": "M071.JPG.jpe", "width": 816, "id": "b30b278daf4eb206dfa1a2c076405697", "height": 1054, "thumbnail": true}, "saison": "Summer / \u00c9t\u00e9", "english_name_nom_en_anglais": "Arrow", "french_name_nom_francais": "Fl\u00e8che", "annee": "1746", "dec": "+18:46:42.2", "dimension": "6,1'", "ra": "19:53:46.11"}, "record_timestamp": "2019-03-05T10:44:29.021+01:00"},{"datasetid": "catalogue-de-messier", "recordid": "54d6807910bcab31e24fe7d35438ee13a956fb02", "fields": {"objet": "Galaxy / Galaxie", "const": "Com", "mag": 10, "decouvreur": "M\u00e9chain", "distance": 36000000, "image": "http://www.lasam.ca/messier/M098.JPG", "ngc": "NGC 4192", "latin_name_nom_latin": "Coma Berenices", "messier": "M98", "image_url": {"mimetype": "image/jpeg", "format": "JPEG", "color_summary": ["rgba(242, 241, 241, 1.00)", "rgba(252, 251, 251, 1.00)", "rgba(249, 248, 248, 1.00)"], "filename": "M098.JPG.jpe", "width": 816, "id": "8d5ed4e0abe4747874fec92578f50b4a", "height": 1054, "thumbnail": true}, "saison": "Spring / Printemps", "english_name_nom_en_anglais": "Hair of Berenice", "french_name_nom_francais": "Chevelure de B\u00e9r\u00e9nice", "annee": "1781", "dec": "+14:54:01.2", "dimension": "9,5' x 3,2'", "ra": "12:13:48.29"}, "record_timestamp": "2019-03-05T10:44:29.021+01:00"},{"datasetid": "catalogue-de-messier", "recordid": "0ebf3d10cb0145d80a354c35a123d04547e13b9b", "fields": {"objet": "Galaxy / Galaxie", "decouvreur": "M\u00e9chain", "distance": 23000000, "image": "http://www.lasam.ca/messier/M102.JPG", "ngc": "NGC 5866", "messier": "M102", "image_url": {"mimetype": "image/jpeg", "format": "JPEG", "color_summary": ["rgba(241, 240, 240, 1.00)", "rgba(253, 252, 252, 1.00)", "rgba(250, 249, 249, 1.00)"], "filename": "M102.JPG.jpe", "width": 816, "id": "be672217c1adf046a98269febe970de4", "height": 1054, "thumbnail": true}, "saison": "Spring / Printemps", "mag": 10, "annee": "1781", "dimension": "5,2' x 2,3'"}, "record_timestamp": "2019-03-05T10:44:29.021+01:00"},{"datasetid": "catalogue-de-messier", "recordid": "f4d81807918cac30842aaea55affb9f95b185f41", "fields": {"objet": "Open Cluster / Amas Ouvert", "const": "Cas", "mag": 7, "decouvreur": "M\u00e9chain", "distance": 8500, "image": "http://www.lasam.ca/messier/M103.JPG", "ngc": "NGC 581", "latin_name_nom_latin": "Cassiopeia", "messier": "M103", "image_url": {"mimetype": "image/jpeg", "format": "JPEG", "color_summary": ["rgba(240, 240, 240, 1.00)", "rgba(206, 205, 205, 1.00)", "rgba(231, 230, 230, 1.00)"], "filename": "M103.JPG.jpe", "width": 816, "id": "e78e6f4f80a2ae2cb8197aa0740ad975", "height": 1054, "thumbnail": true}, "saison": "Autumn / Automne", "english_name_nom_en_anglais": "Cassiopeia", "french_name_nom_francais": "Cassiop\u00e9e", "annee": "1781", "dec": "+60:39:28.8", "dimension": "5,0'", "ra": "01:33:21.81"}, "record_timestamp": "2019-03-05T10:44:29.021+01:00"},{"datasetid": "catalogue-de-messier", "recordid": "b4feffd7a52b297c5b76c325253c488a9ca868bb", "fields": {"objet": "Galaxy / Galaxie", "const": "CVn", "mag": 8, "decouvreur": "M\u00e9chain", "distance": 20000000, "image": "http://www.lasam.ca/messier/M106.JPG", "ngc": "NGC 4258", "latin_name_nom_latin": "Canes Venatici", "messier": "M106", "image_url": {"mimetype": "image/jpeg", "format": "JPEG", "color_summary": ["rgba(240, 239, 239, 1.00)", "rgba(253, 252, 252, 1.00)", "rgba(250, 250, 250, 1.00)"], "filename": "M106.JPG.jpe", "width": 816, "id": "3652e8d678cf1a56720bf0e86e38fa20", "height": 1054, "thumbnail": true}, "saison": "Spring / Printemps", "english_name_nom_en_anglais": "Hound Dogs", "french_name_nom_francais": "Les\u00a0Chiens de chasse", "annee": "1781", "dec": "+47:18:14.3", "dimension": "18,0' x 7,9'", "ra": "12:18:57.50"}, "record_timestamp": "2019-03-05T10:44:29.021+01:00"},{"datasetid": "catalogue-de-messier", "recordid": "3a30daa6df575f943d43ca385d047270f83bf0ae", "fields": {"objet": "Globular Cluster / Amas Globulaire", "const": "Sgr", "mag": 8, "decouvreur": "Messier", "distance": 65000, "image": "http://www.lasam.ca/messier/M070.JPG", "ngc": "NGC 6681", "latin_name_nom_latin": "Sagittarius", "messier": "M70", "image_url": {"mimetype": "image/jpeg", "format": "JPEG", "color_summary": ["rgba(189, 188, 189, 1.00)", "rgba(201, 200, 200, 1.00)", "rgba(227, 226, 226, 1.00)"], "filename": "M070.JPG.jpe", "width": 816, "id": "e664481efead034f54af20e50bfce8f0", "height": 1054, "thumbnail": true}, "saison": "Summer / \u00c9t\u00e9", "english_name_nom_en_anglais": "Archer", "french_name_nom_francais": "Sagittaire", "annee": "1780", "dec": "-32:17:30.8", "dimension": "4,1'", "ra": "18:43:12.64"}, "record_timestamp": "2019-03-05T10:44:29.021+01:00"},{"datasetid": "catalogue-de-messier", "recordid": "c56c9f200c2aa5711548ae997bab7866912eadbc", "fields": {"objet": "Open Cluster / Amas Ouvert", "const": "Mon", "mag": 5, "decouvreur": "Cassini", "distance": 2950, "image": "http://www.lasam.ca/messier/M050.JPG", "ngc": "NGC 2323", "latin_name_nom_latin": "Monoceros", "messier": "M50", "image_url": {"mimetype": "image/jpeg", "format": "JPEG", "color_summary": ["rgba(201, 201, 201, 1.00)", "rgba(221, 220, 220, 1.00)", "rgba(224, 224, 224, 1.00)"], "filename": "M050.JPG.jpe", "width": 816, "id": "b57cd7278a77f27db822dc3b2a3fd330", "height": 1054, "thumbnail": true}, "saison": "Winter / Hiver", "english_name_nom_en_anglais": "Unicorn", "french_name_nom_francais": "Licorne", "annee": "1710", "dec": "-08:21:50.5", "dimension": "16,0. x 5,5'", "ra": "07:02:40.47"}, "record_timestamp": "2019-03-05T10:44:29.021+01:00"},{"datasetid": "catalogue-de-messier", "recordid": "1e68cb201748947cf8dbdf676c0f8d6c05ecd4ac", "fields": {"objet": "Galaxy / Galaxie", "const": "Vir", "mag": 9, "decouvreur": "Oriani", "distance": 41000000, "image": "http://www.lasam.ca/messier/M061.JPG", "ngc": "NGC 4303", "latin_name_nom_latin": "Virgo", "messier": "M61", "image_url": {"mimetype": "image/jpeg", "format": "JPEG", "color_summary": ["rgba(241, 239, 239, 1.00)", "rgba(251, 251, 251, 1.00)", "rgba(249, 249, 249, 1.00)"], "filename": "M061.JPG.jpe", "width": 816, "id": "93c04111b9eea5f01925db31d67bb866", "height": 1054, "thumbnail": true}, "saison": "Spring / Printemps", "english_name_nom_en_anglais": "Virgin", "french_name_nom_francais": "Vierge", "annee": "1779", "dec": "+04:28:25.1", "dimension": "6,0' x 5,5'", "ra": "12:21:54.90"}, "record_timestamp": "2019-03-05T10:44:29.021+01:00"},{"datasetid": "catalogue-de-messier", "recordid": "65abba2f90d219671c1b2cfec5a2a604e45c4277", "fields": {"objet": "Double star / \u00c9toile Double", "decouvreur": "Hevelius", "ngc": "Winnecke 4", "image": "http://www.lasam.ca/messier/M040.JPG", "messier": "M40", "image_url": {"mimetype": "image/jpeg", "format": "JPEG", "color_summary": ["rgba(240, 240, 240, 1.00)", "rgba(252, 251, 251, 1.00)", "rgba(250, 250, 250, 1.00)"], "filename": "M040.JPG.jpe", "width": 816, "id": "86cc361448cba451bb6dd75a43e55d23", "height": 1054, "thumbnail": true}, "saison": "Spring / Printemps", "mag": 9, "annee": "1660"}, "record_timestamp": "2019-03-05T10:44:29.021+01:00"},{"datasetid": "catalogue-de-messier", "recordid": "2fffb7ef8521c24d65b61ddd59e89338d068ed33", "fields": {"objet": "Galaxy / Galaxie", "const": "CVn", "mag": 8, "decouvreur": "M\u00e9chain", "distance": 32600000, "image": "http://www.lasam.ca/messier/M094.JPG", "ngc": "NGC 4736", "latin_name_nom_latin": "Canes Venatici", "messier": "M94", "image_url": {"mimetype": "image/jpeg", "format": "JPEG", "color_summary": ["rgba(241, 240, 240, 1.00)", "rgba(253, 252, 252, 1.00)", "rgba(250, 250, 250, 1.00)"], "filename": "M094.JPG.jpe", "width": 816, "id": "8c106b857bd4916cfc4712b82690df78", "height": 1054, "thumbnail": true}, "saison": "Spring / Printemps", "english_name_nom_en_anglais": "Hound Dogs", "french_name_nom_francais": "Les\u00a0Chiens de chasse", "annee": "1781", "dec": "+41:07:13.6", "dimension": "11,0' x 9,1'", "ra": "12:50:53.06"}, "record_timestamp": "2019-03-05T10:44:29.021+01:00"},{"datasetid": "catalogue-de-messier", "recordid": "117d04010ac443aa0b6cc68478d17cf820a150d6", "fields": {"objet": "Planetary Nebula / N\u00e9buleuse Plan\u00e9taire", "const": "UMa", "mag": 11, "decouvreur": "M\u00e9chain", "distance": 10000, "image": "http://www.lasam.ca/messier/M097.JPG", "ngc": "NGC 3587", "latin_name_nom_latin": "Ursa Major", "messier": "M97", "image_url": {"mimetype": "image/jpeg", "format": "JPEG", "color_summary": ["rgba(240, 240, 240, 1.00)", "rgba(252, 252, 252, 1.00)", "rgba(250, 250, 250, 1.00)"], "filename": "M097.JPG.jpe", "width": 816, "id": "d744f41706a9b3810b36584de9d75801", "height": 1054, "thumbnail": true}, "saison": "Spring / Printemps", "english_name_nom_en_anglais": "Big Bear", "french_name_nom_francais": "Grande Ourse", "annee": "1781", "dec": "+55:01:08.5", "dimension": "194''", "ra": "11:14:47.71"}, "record_timestamp": "2019-03-05T10:44:29.021+01:00"},{"datasetid": "catalogue-de-messier", "recordid": "94859a7addaa23df0fe0f69b4bdf0a54498bdc0d", "fields": {"objet": "Galaxy / Galaxie", "const": "UMa", "mag": 6, "decouvreur": "Bode", "distance": 8500000, "image": "http://www.lasam.ca/messier/M081.JPG", "ngc": "NGC 3031", "latin_name_nom_latin": "Ursa Major", "messier": "M81", "image_url": {"mimetype": "image/jpeg", "format": "JPEG", "color_summary": ["rgba(242, 241, 241, 1.00)", "rgba(253, 252, 252, 1.00)", "rgba(249, 248, 249, 1.00)"], "filename": "M081.JPG.jpe", "width": 816, "id": "98b8df1b91995265cc8974c72394d802", "height": 1054, "thumbnail": true}, "saison": "Spring / Printemps", "english_name_nom_en_anglais": "Big Bear", "french_name_nom_francais": "Grande Ourse", "annee": "1774", "dec": "+69:03:55.1", "dimension": "26,0' x 14,0'", "ra": "09:55:33.17"}, "record_timestamp": "2019-03-05T10:44:29.021+01:00"},{"datasetid": "catalogue-de-messier", "recordid": "253d9c09aede7c59fdcca28e15df0cba0199b502", "fields": {"objet": "Globular Cluster / Amas Globulaire", "const": "Her", "mag": 6, "decouvreur": "Bode", "distance": 28400, "image": "http://www.lasam.ca/messier/M092.JPG", "ngc": "NGC 6341", "latin_name_nom_latin": "Hercules", "messier": "M92", "image_url": {"mimetype": "image/jpeg", "format": "JPEG", "color_summary": ["rgba(240, 240, 240, 1.00)", "rgba(252, 252, 252, 1.00)", "rgba(249, 249, 249, 1.00)"], "filename": "M092.JPG.jpe", "width": 816, "id": "6c4a2a8d2f30863dd42d987e71d9fa31", "height": 1054, "thumbnail": true}, "saison": "Summer / \u00c9t\u00e9", "english_name_nom_en_anglais": "Hercules", "french_name_nom_francais": "Hercule", "annee": "1777", "dec": "+43:08:11.5", "dimension": "12,2'", "ra": "17:17:07.27"}, "record_timestamp": "2019-03-05T10:44:29.021+01:00"},{"datasetid": "catalogue-de-messier", "recordid": "3a2c6caa9e7961e3a9c96b700ded60f63edb09fe", "fields": {"objet": "Galaxy / Galaxie", "const": "Vir", "mag": 9, "decouvreur": "Messier", "distance": 41000000, "image": "http://www.lasam.ca/messier/M090.JPG", "ngc": "NGC 4560", "latin_name_nom_latin": "Virgo", "messier": "M90", "image_url": {"mimetype": "image/jpeg", "format": "JPEG", "color_summary": ["rgba(241, 240, 240, 1.00)", "rgba(252, 251, 251, 1.00)", "rgba(249, 248, 248, 1.00)"], "filename": "M090.JPG.jpe", "width": 816, "id": "24533f4722df7e1a3a89b6314be09bcd", "height": 1054, "thumbnail": true}, "saison": "Spring / Printemps", "english_name_nom_en_anglais": "Virgin", "french_name_nom_francais": "Vierge", "annee": "1781", "dec": "+13:09:46.6", "dimension": "9,5' x 4,7'", "ra": "12:36:49.79"}, "record_timestamp": "2019-03-05T10:44:29.021+01:00"},{"datasetid": "catalogue-de-messier", "recordid": "93bfd492e9a29519ba50c152095939dbe6f38397", "fields": {"objet": "Galaxy / Galaxie", "const": "Vir", "mag": 8, "decouvreur": "Messier", "distance": 63000000, "image": "http://www.lasam.ca/messier/M087.JPG", "ngc": "NGC 4486", "latin_name_nom_latin": "Virgo", "messier": "M87", "image_url": {"mimetype": "image/jpeg", "format": "JPEG", "color_summary": ["rgba(241, 240, 240, 1.00)", "rgba(252, 251, 251, 1.00)", "rgba(249, 248, 248, 1.00)"], "filename": "M087.JPG.jpe", "width": 816, "id": "23f8026f16d2f4c0e59b77f9c33a5917", "height": 1054, "thumbnail": true}, "saison": "Spring / Printemps", "english_name_nom_en_anglais": "Virgin", "french_name_nom_francais": "Vierge", "annee": "1781", "dec": "+12:23:28.0", "dimension": "7,2' x 6,8'", "ra": "12:30:49.42"}, "record_timestamp": "2019-03-05T10:44:29.021+01:00"},{"datasetid": "catalogue-de-messier", "recordid": "a5e6f14ba70225c1b1445bef89953ef99ecc57ac", "fields": {"objet": "Globular Cluster / Amas Globulaire", "const": "Aqr", "mag": 6, "decouvreur": "Maraldi", "distance": 55000, "image": "http://www.lasam.ca/messier/M002.JPG", "ngc": "NGC 7089", "latin_name_nom_latin": "Aquarius", "messier": "M2", "image_url": {"mimetype": "image/jpeg", "format": "JPEG", "color_summary": ["rgba(240, 239, 239, 1.00)", "rgba(253, 252, 252, 1.00)", "rgba(249, 249, 249, 1.00)"], "filename": "M002.JPG.jpe", "width": 816, "id": "72a28fa7cc3d992875d9228e54c1027a", "height": 1054, "thumbnail": true}, "saison": "Autumn / Automne", "english_name_nom_en_anglais": "Water Bearer", "french_name_nom_francais": "Verseau", "annee": "1746", "dec": "-00:49:23.9", "dimension": "11,7'", "ra": "21:33:27.01"}, "record_timestamp": "2019-03-05T10:44:29.021+01:00"},{"datasetid": "catalogue-de-messier", "recordid": "9cd8e4f0feb46bd6e414061f2b6171f9e3bcf6c5", "fields": {"objet": "Open Cluster / Amas Ouvert", "const": "Sco", "mag": 4, "decouvreur": "Hodierna", "distance": 1300, "image": "http://www.lasam.ca/messier/M006.JPG", "ngc": "NGC 6504", "latin_name_nom_latin": "Scorpius", "messier": "M6", "image_url": {"mimetype": "image/jpeg", "format": "JPEG", "color_summary": ["rgba(182, 181, 182, 1.00)", "rgba(186, 185, 185, 1.00)", "rgba(192, 191, 191, 1.00)"], "filename": "M006.JPG.jpe", "width": 816, "id": "76fec88c92a5b715e2d1d7aa5e5f47bf", "height": 1054, "thumbnail": true}, "saison": "Summer / \u00c9t\u00e9", "english_name_nom_en_anglais": "Scorpion", "french_name_nom_francais": "Scorpion", "annee": "1654", "dec": "-32:15:15.0", "dimension": "15,0'", "ra": "17:40:20.75"}, "record_timestamp": "2019-03-05T10:44:29.021+01:00"},{"datasetid": "catalogue-de-messier", "recordid": "de7f6e6fb1489d10fa53b04e69ec13d88b6b6525", "fields": {"objet": "Emission Nebula / N\u00e9buleuse \u00e0 \u00e9mission", "const": "Sgr", "mag": 6, "decouvreur": "Ch\u00e9seaux", "distance": 5870, "image": "http://www.lasam.ca/messier/M017.JPG", "ngc": "NGC 6618", "latin_name_nom_latin": "Sagittarius", "messier": "M17", "image_url": {"mimetype": "image/jpeg", "format": "JPEG", "color_summary": ["rgba(222, 222, 222, 1.00)", "rgba(203, 202, 202, 1.00)", "rgba(184, 182, 183, 1.00)"], "filename": "M017.JPG.jpe", "width": 816, "id": "12d9d5ca3b75f3157f4c82de00a17864", "height": 1054, "thumbnail": true}, "saison": "Summer / \u00c9t\u00e9", "english_name_nom_en_anglais": "Archer", "french_name_nom_francais": "Sagittaire", "annee": "1746", "dec": "-16:10:17.5", "dimension": "45,0' x 35,0'", "ra": "18:20:47.11"}, "record_timestamp": "2019-03-05T10:44:29.021+01:00"},{"datasetid": "catalogue-de-messier", "recordid": "639f792ca54b38f664b558943a986024b1cee254", "fields": {"objet": "Planetary Nebula / N\u00e9buleuse Plan\u00e9taire", "const": "Vul", "mag": 8, "decouvreur": "Messier", "distance": 980, "image": "http://www.lasam.ca/messier/M027.JPG", "ngc": "NGC 6853", "latin_name_nom_latin": "Vulpecula", "messier": "M27", "image_url": {"mimetype": "image/jpeg", "format": "JPEG", "color_summary": ["rgba(188, 187, 187, 1.00)", "rgba(213, 212, 212, 1.00)", "rgba(219, 218, 218, 1.00)"], "filename": "M027.JPG.jpe", "width": 816, "id": "5494a23d572d4041e15188e415c463a0", "height": 1054, "thumbnail": true}, "saison": "Summer / \u00c9t\u00e9", "english_name_nom_en_anglais": "Little Fox", "french_name_nom_francais": "Petit Renard", "annee": "1764", "dec": "+22:43:15.7", "dimension": "348,0''", "ra": "19:59:36.38"}, "record_timestamp": "2019-03-05T10:44:29.021+01:00"},{"datasetid": "catalogue-de-messier", "recordid": "2ab6ebd2d2756d678b215ea3b0d69d48e7c64338", "fields": {"objet": "Globular Cluster / Amas Globulaire", "const": "Sgr", "mag": 6, "decouvreur": "Messier", "distance": 19000, "image": "http://www.lasam.ca/messier/M028.JPG", "ngc": "NGC 6626", "latin_name_nom_latin": "Sagittarius", "messier": "M28", "image_url": {"mimetype": "image/jpeg", "format": "JPEG", "color_summary": ["rgba(197, 196, 196, 1.00)", "rgba(188, 186, 187, 1.00)", "rgba(191, 190, 190, 1.00)"], "filename": "M028.JPG.jpe", "width": 816, "id": "c4787a8e91306e913db4e32168b34622", "height": 1054, "thumbnail": true}, "saison": "Summer / \u00c9t\u00e9", "english_name_nom_en_anglais": "Archer", "french_name_nom_francais": "Sagittaire", "annee": "1764", "dec": "-24:52:11.4", "dimension": "15,0'", "ra": "18:24:32.89"}, "record_timestamp": "2019-03-05T10:44:29.021+01:00"},{"datasetid": "catalogue-de-messier", "recordid": "be63ccade50692c9fe414f04fb54c60c20032fa9", "fields": {"objet": "Galaxy / Galaxie", "const": "UMa", "mag": 7, "decouvreur": "M\u00e9chain", "distance": 23000000, "image": "http://www.lasam.ca/messier/M101.JPG", "ngc": "NGC 5457", "latin_name_nom_latin": "Ursa Major", "messier": "M101", "image_url": {"mimetype": "image/jpeg", "format": "JPEG", "color_summary": ["rgba(241, 240, 240, 1.00)", "rgba(252, 252, 252, 1.00)", "rgba(250, 250, 250, 1.00)"], "filename": "M101.JPG.jpe", "width": 816, "id": "0eb14758ee56fb463d6f42d798673e4f", "height": 1054, "thumbnail": true}, "saison": "Spring / Printemps", "english_name_nom_en_anglais": "Big Bear", "french_name_nom_francais": "Grande Ourse", "annee": "1781", "dec": "+54:20:56.2", "dimension": "27,0' x 26,0'", "ra": "14:03:12.54"}, "record_timestamp": "2019-03-05T10:44:29.021+01:00"},{"datasetid": "catalogue-de-messier", "recordid": "5c46ca0f8251b16d0894e276a3990104686d8f1d", "fields": {"objet": "Galaxy / Galaxie", "const": "Com", "mag": 9, "decouvreur": "M\u00e9chain", "distance": 41000000, "image": "http://www.lasam.ca/messier/M085.JPG", "ngc": "NGC 4382", "latin_name_nom_latin": "Coma Berenices", "messier": "M85", "image_url": {"mimetype": "image/jpeg", "format": "JPEG", "color_summary": ["rgba(242, 241, 241, 1.00)", "rgba(252, 251, 251, 1.00)", "rgba(249, 248, 248, 1.00)"], "filename": "M085.JPG.jpe", "width": 816, "id": "6f5ba5b373b9d98409c648eccca69991", "height": 1054, "thumbnail": true}, "saison": "Spring / Printemps", "english_name_nom_en_anglais": "Hair of Berenice", "french_name_nom_francais": "Chevelure de B\u00e9r\u00e9nice", "annee": "1781", "dec": "+18:11:29.4", "dimension": "7,1' x 5,2'", "ra": "12:25:24.11"}, "record_timestamp": "2019-03-05T10:44:29.021+01:00"},{"datasetid": "catalogue-de-messier", "recordid": "aada6474e7e3a7112ffa454a3e49e5009b45af79", "fields": {"objet": "Galaxy / Galaxie", "const": "CVn", "mag": 8, "decouvreur": "M\u00e9chain", "distance": 23800000, "image": "http://www.lasam.ca/messier/M063.JPG", "ngc": "NGC 5055", "latin_name_nom_latin": "Canes Venatici", "messier": "M63", "image_url": {"mimetype": "image/jpeg", "format": "JPEG", "color_summary": ["rgba(241, 240, 240, 1.00)", "rgba(253, 252, 252, 1.00)", "rgba(251, 250, 250, 1.00)"], "filename": "M063.JPG.jpe", "width": 816, "id": "6cc3be477870d7c2a23c13181ba4ce0c", "height": 1054, "thumbnail": true}, "saison": "Spring / Printemps", "english_name_nom_en_anglais": "Hound Dogs", "french_name_nom_francais": "Les\u00a0Chiens de chasse", "annee": "1779", "dec": "+42:01:45.4", "dimension": "12,0' x 7,6'", "ra": "13:15:49.33"}, "record_timestamp": "2019-03-05T10:44:29.021+01:00"},{"datasetid": "catalogue-de-messier", "recordid": "cb160838a0c6a54585a2f03b2781d6fd1c64a217", "fields": {"objet": "Planetary Nebula / N\u00e9buleuse Plan\u00e9taire", "const": "Per", "mag": 10, "decouvreur": "M\u00e9chain", "distance": 8200, "image": "http://www.lasam.ca/messier/M076.JPG", "ngc": "NGC 650", "latin_name_nom_latin": "Perseus", "messier": "M76", "image_url": {"mimetype": "image/jpeg", "format": "JPEG", "color_summary": ["rgba(197, 196, 196, 1.00)", "rgba(227, 226, 226, 1.00)", "rgba(252, 252, 252, 1.00)"], "filename": "M076.JPG.jpe", "width": 816, "id": "10b05a2559cec6958f11f28d915602c4", "height": 1054, "thumbnail": true}, "saison": "Autumn / Automne", "english_name_nom_en_anglais": "Perseus", "french_name_nom_francais": "Pers\u00e9e", "annee": "1780", "dec": "+51:34:31.7", "dimension": "65''", "ra": "01:42:19.69"}, "record_timestamp": "2019-03-05T10:44:29.021+01:00"},{"datasetid": "catalogue-de-messier", "recordid": "5a0e0f94c780319a47fe86f05d539c0b44629655", "fields": {"objet": "Globular Cluster / Amas Globulaire", "const": "Sco", "mag": 7, "decouvreur": "Messier", "distance": 36000, "image": "http://www.lasam.ca/messier/M080.JPG", "ngc": "NGC 6093", "latin_name_nom_latin": "Scorpius", "messier": "M80", "image_url": {"mimetype": "image/jpeg", "format": "JPEG", "color_summary": ["rgba(240, 239, 240, 1.00)", "rgba(238, 237, 239, 1.00)", "rgba(232, 231, 231, 1.00)"], "filename": "M080.JPG.jpe", "width": 816, "id": "888d3682b7378784f02c2fbae70bdcfc", "height": 1054, "thumbnail": true}, "saison": "Summer / \u00c9t\u00e9", "english_name_nom_en_anglais": "Scorpion", "french_name_nom_francais": "Scorpion", "annee": "1781", "dec": "-22:58:30.4", "dimension": "5,1'", "ra": "16:17:02.51"}, "record_timestamp": "2019-03-05T10:44:29.021+01:00"},{"datasetid": "catalogue-de-messier", "recordid": "59ca87a232670caf14b2d78ffedba001c56abb18", "fields": {"objet": "Open Cluster / Amas Ouvert", "const": "Pup", "mag": 6, "decouvreur": "Messier", "distance": 3600, "image": "http://www.lasam.ca/messier/M093.JPG", "ngc": "NGC 2447", "latin_name_nom_latin": "Puppis", "messier": "M93", "image_url": {"mimetype": "image/jpeg", "format": "JPEG", "color_summary": ["rgba(207, 207, 207, 1.00)", "rgba(211, 210, 210, 1.00)", "rgba(231, 230, 230, 1.00)"], "filename": "M093.JPG.jpe", "width": 816, "id": "6e8bd0766f6b700b69f752b705affb23", "height": 1054, "thumbnail": true}, "saison": "Winter / Hiver", "english_name_nom_en_anglais": "Stern,Poop deck", "french_name_nom_francais": "Poupe", "annee": "1781", "dec": "-23:51:11.1", "dimension": "22,0'", "ra": "07:44:29.23"}, "record_timestamp": "2019-03-05T10:44:29.021+01:00"},{"datasetid": "catalogue-de-messier", "recordid": "7840a5185db060dcc0c219ca1267be947c80bc8d", "fields": {"objet": "Galaxy / Galaxie", "const": "Psc", "mag": 9, "decouvreur": "M\u00e9chain", "distance": 26000000, "image": "http://www.lasam.ca/messier/M074.JPG", "ngc": "NGC 628", "latin_name_nom_latin": "Pisces", "messier": "M74", "image_url": {"mimetype": "image/jpeg", "format": "JPEG", "color_summary": ["rgba(241, 240, 240, 1.00)", "rgba(253, 252, 252, 1.00)", "rgba(249, 249, 249, 1.00)"], "filename": "M074.JPG.jpe", "width": 816, "id": "366e8c3e374eec05b66820745c8bfddb", "height": 1054, "thumbnail": true}, "saison": "Autumn / Automne", "english_name_nom_en_anglais": "Fishes", "french_name_nom_francais": "Les\u00a0Poissons", "annee": "1780", "dec": "+15:47:01.2", "dimension": "10,0' x 9,6'", "ra": "01:36:41.75"}, "record_timestamp": "2019-03-05T10:44:29.021+01:00"},{"datasetid": "catalogue-de-messier", "recordid": "00f22385373cd4984aab0dc46faf7c269aed8bc7", "fields": {"objet": "Galaxy / Galaxie", "const": "Vir", "mag": 9, "decouvreur": "Messier", "distance": 41000000, "image": "http://www.lasam.ca/messier/M089.JPG", "ngc": "NGC 4552", "latin_name_nom_latin": "Virgo", "messier": "M89", "image_url": {"mimetype": "image/jpeg", "format": "JPEG", "color_summary": ["rgba(241, 240, 240, 1.00)", "rgba(252, 251, 251, 1.00)", "rgba(249, 248, 248, 1.00)"], "filename": "M089.JPG.jpe", "width": 816, "id": "7dfedc34971b44cb118da7a04dc35c9f", "height": 1054, "thumbnail": true}, "saison": "Spring / Printemps", "english_name_nom_en_anglais": "Virgin", "french_name_nom_francais": "Vierge", "annee": "1781", "dec": "+12:33:22.8", "dimension": "4,2' x 4,2'", "ra": "12:35:39.81"}, "record_timestamp": "2019-03-05T10:44:29.021+01:00"},{"datasetid": "catalogue-de-messier", "recordid": "d668760d5ac4e80fdf0b17dc72c697e6cb8345ce", "fields": {"objet": "Open Cluster / Amas Ouvert", "const": "Aur", "mag": 5, "decouvreur": "Hodierna", "distance": 3600, "image": "http://www.lasam.ca/messier/M037.JPG", "ngc": "NGC 2099", "latin_name_nom_latin": "Auriga", "messier": "M37", "image_url": {"mimetype": "image/jpeg", "format": "JPEG", "color_summary": ["rgba(220, 220, 220, 1.00)", "rgba(210, 209, 209, 1.00)", "rgba(206, 205, 206, 1.00)"], "filename": "M037.JPG.jpe", "width": 816, "id": "7e17ed527b55fc1b1afad4bae9f26e47", "height": 1054, "thumbnail": true}, "saison": "Winter / Hiver", "english_name_nom_en_anglais": "Charioteer", "french_name_nom_francais": "Cocher", "annee": "1654", "dec": "+32:33:10.8", "dimension": "24,0'", "ra": "05:52:18.35"}, "record_timestamp": "2019-03-05T10:44:29.021+01:00"},{"datasetid": "catalogue-de-messier", "recordid": "30e2b12cdbb38d2dae6a79261c809b3839fec934", "fields": {"objet": "Open Cluster / Amas Ouvert", "const": "Aur", "mag": 6, "decouvreur": "Hodierna", "distance": 3700, "image": "http://www.lasam.ca/messier/M036.JPG", "ngc": "NGC 1960", "latin_name_nom_latin": "Auriga", "messier": "M36", "image_url": {"mimetype": "image/jpeg", "format": "JPEG", "color_summary": ["rgba(220, 219, 219, 1.00)", "rgba(208, 207, 208, 1.00)", "rgba(218, 217, 218, 1.00)"], "filename": "M036.JPG.jpe", "width": 816, "id": "9121fd0c5dbdb9e77449ba6122791371", "height": 1054, "thumbnail": true}, "saison": "Winter / Hiver", "english_name_nom_en_anglais": "Charioteer", "french_name_nom_francais": "Cocher", "annee": "1654", "dec": "+34:08:26.7", "dimension": "12,0'", "ra": "05:36:17.74"}, "record_timestamp": "2019-03-05T10:44:29.021+01:00"},{"datasetid": "catalogue-de-messier", "recordid": "ad604cb621492d541c5b078f7d7479cad3ae45dc", "fields": {"objet": "Open Cluster / Amas Ouvert", "const": "Hya", "mag": 5, "decouvreur": "Messier", "distance": 1500, "image": "http://www.lasam.ca/messier/M048.JPG", "ngc": "NGC 2548", "latin_name_nom_latin": "Hydra", "messier": "M48", "image_url": {"mimetype": "image/jpeg", "format": "JPEG", "color_summary": ["rgba(239, 238, 238, 1.00)", "rgba(247, 246, 246, 1.00)", "rgba(226, 226, 226, 1.00)"], "filename": "M048.JPG.jpe", "width": 816, "id": "e8265fa1084e9c84c45892bc7bf6c67e", "height": 1054, "thumbnail": true}, "saison": "Winter / Hiver", "english_name_nom_en_anglais": "Hydra, Sea Snake", "french_name_nom_francais": "Hydre", "annee": "1771", "dec": "-05:45:01.6", "dimension": "42'", "ra": "08:13:43.18"}, "record_timestamp": "2019-03-05T10:44:29.021+01:00"},{"datasetid": "catalogue-de-messier", "recordid": "989b38b45acaf01958f343c26cf04467ee091387", "fields": {"objet": "Galaxy / Galaxie", "const": "And", "mag": 3, "distance": 2500000, "image": "http://www.lasam.ca/messier/M031.JPG", "ngc": "NGC 224", "latin_name_nom_latin": "Andromeda", "messier": "M31", "image_url": {"mimetype": "image/jpeg", "format": "JPEG", "color_summary": ["rgba(220, 219, 220, 1.00)", "rgba(252, 252, 252, 1.00)", "rgba(249, 248, 248, 1.00)"], "filename": "M031.JPG.jpe", "width": 816, "id": "8b09c0b962eacd7c73b3654173640a72", "height": 1054, "thumbnail": true}, "saison": "Autumn / Automne", "english_name_nom_en_anglais": "Andromeda", "french_name_nom_francais": "Androm\u00e8de", "dec": "+41:16:08.6", "dimension": "180,0' x 63,0'", "ra": "00:42:44.35"}, "record_timestamp": "2019-03-05T10:44:29.021+01:00"},{"datasetid": "catalogue-de-messier", "recordid": "2d8df4c16bece39640643bcc1f3f506a5a3a6e9b", "fields": {"objet": "Galaxy / Galaxie", "const": "Crv", "mag": 8, "decouvreur": "M\u00e9chain", "distance": 40000000, "image": "http://www.lasam.ca/messier/M104.JPG", "ngc": "NGC 4594", "latin_name_nom_latin": "Corvus", "messier": "M104", "image_url": {"mimetype": "image/jpeg", "format": "JPEG", "color_summary": ["rgba(240, 240, 240, 1.00)", "rgba(252, 252, 252, 1.00)", "rgba(250, 249, 249, 1.00)"], "filename": "M104.JPG.jpe", "width": 816, "id": "98ca6645bb15fb146eb24174c1385fe0", "height": 1054, "thumbnail": true}, "saison": "Spring / Printemps", "english_name_nom_en_anglais": "Crow", "french_name_nom_francais": "Corbeau", "annee": "1781", "dec": "-11:37:23.0", "dimension": "8,9' x 4,1'", "ra": "12:39:59.43"}, "record_timestamp": "2019-03-05T10:44:29.021+01:00"},{"datasetid": "catalogue-de-messier", "recordid": "4bec0c91896e4830e1d9b5f79df021b55b949e1f", "fields": {"objet": "Galaxy / Galaxie", "const": "Leo", "mag": 9, "decouvreur": "M\u00e9chain", "distance": 21500000, "image": "http://www.lasam.ca/messier/M105.JPG", "ngc": "NGC 3379", "latin_name_nom_latin": "Leo", "messier": "M105", "image_url": {"mimetype": "image/jpeg", "format": "JPEG", "color_summary": ["rgba(241, 241, 241, 1.00)", "rgba(251, 251, 251, 1.00)", "rgba(250, 250, 250, 1.00)"], "filename": "M105.JPG.jpe", "width": 816, "id": "980658767f5f4f8f0257e06b67164cdd", "height": 1054, "thumbnail": true}, "saison": "Spring / Printemps", "english_name_nom_en_anglais": "Lion", "french_name_nom_francais": "Lion", "annee": "1781", "dec": "+12:34:53.8", "dimension": "4,5' x 4,0'", "ra": "10:47:49.59"}, "record_timestamp": "2019-03-05T10:44:29.021+01:00"},{"datasetid": "catalogue-de-messier", "recordid": "0be1e70736bf4b50b61b80f681cc632ab761a771", "fields": {"objet": "Galaxy / Galaxie", "const": "Leo", "mag": 9, "decouvreur": "M\u00e9chain", "distance": 29300000, "image": "http://www.lasam.ca/messier/M096.JPG", "ngc": "NGC 3368", "latin_name_nom_latin": "Leo", "messier": "M96", "image_url": {"mimetype": "image/jpeg", "format": "JPEG", "color_summary": ["rgba(241, 240, 240, 1.00)", "rgba(251, 251, 251, 1.00)", "rgba(250, 250, 250, 1.00)"], "filename": "M096.JPG.jpe", "width": 816, "id": "1bd1d0aa2825496929c004902ef49884", "height": 1054, "thumbnail": true}, "saison": "Spring / Printemps", "english_name_nom_en_anglais": "Lion", "french_name_nom_francais": "Lion", "annee": "1781", "dec": "+11:49:11.8", "dimension": "7,1' x 5,1'", "ra": "10:46:45.74"}, "record_timestamp": "2019-03-05T10:44:29.021+01:00"},{"datasetid": "catalogue-de-messier", "recordid": "62e0c1628c18d2cecd5a104833f2cb9cf4019bfa", "fields": {"objet": "Emission Nebula / N\u00e9buleuse \u00e0 \u00e9mission", "const": "Se2", "decouvreur": "Ch\u00e9seaux", "distance": 5870, "image": "http://www.lasam.ca/messier/M016.JPG", "ngc": "NGC 6611", "messier": "M16", "image_url": {"mimetype": "image/jpeg", "format": "JPEG", "color_summary": ["rgba(226, 225, 225, 1.00)", "rgba(212, 210, 211, 1.00)", "rgba(184, 183, 183, 1.00)"], "filename": "M016.JPG.jpe", "width": 816, "id": "815eebcc7d91f614254397f70ef9f3ed", "height": 1054, "thumbnail": true}, "saison": "Summer / \u00c9t\u00e9", "mag": 6, "annee": "1746", "dec": "-13:48:26.0", "dimension": "25,0'", "ra": "18:18:48.17"}, "record_timestamp": "2019-03-05T10:44:29.021+01:00"},{"datasetid": "catalogue-de-messier", "recordid": "4711300aca00784a458bda46fe99907dba2e595f", "fields": {"objet": "Globular Cluster / Amas Globulaire", "const": "Sco", "mag": 5, "decouvreur": "Ch\u00e9seaux", "distance": 9900, "image": "http://www.lasam.ca/messier/M004.JPG", "ngc": "NGC 6121", "latin_name_nom_latin": "Scorpius", "messier": "M4", "image_url": {"mimetype": "image/jpeg", "format": "JPEG", "color_summary": ["rgba(233, 233, 233, 1.00)", "rgba(231, 230, 232, 1.00)", "rgba(224, 224, 224, 1.00)"], "filename": "M004.JPG.jpe", "width": 816, "id": "9e84672c59018c447a8a2b69bd0b00b5", "height": 1054, "thumbnail": true}, "saison": "Summer / \u00c9t\u00e9", "english_name_nom_en_anglais": "Scorpion", "french_name_nom_francais": "Scorpion", "annee": "1746", "dec": "-26:31:31.9", "dimension": "22,8'", "ra": "16:23:35.40"}, "record_timestamp": "2019-03-05T10:44:29.021+01:00"},{"datasetid": "catalogue-de-messier", "recordid": "b5c377ae83265de71ae922f56f1dc31a5d0af808", "fields": {"objet": "Globular Cluster / Amas Globulaire", "const": "Peg", "mag": 6, "decouvreur": "Maraldi", "distance": 49500, "image": "http://www.lasam.ca/messier/M015.JPG", "ngc": "NGC 7078", "latin_name_nom_latin": "Pegasus", "messier": "M15", "image_url": {"mimetype": "image/jpeg", "format": "JPEG", "color_summary": ["rgba(238, 237, 237, 1.00)", "rgba(252, 251, 251, 1.00)", "rgba(250, 249, 249, 1.00)"], "filename": "M015.JPG.jpe", "width": 816, "id": "28bacad1602d1b9a95f5586e8b74ce3e", "height": 1054, "thumbnail": true}, "saison": "Autumn / Automne", "english_name_nom_en_anglais": "Winged Horse", "french_name_nom_francais": "P\u00e9gase", "annee": "1746", "dec": "+12:10:00.6", "dimension": "12,3'", "ra": "21:29:58.38"}, "record_timestamp": "2019-03-05T10:44:29.021+01:00"},{"datasetid": "catalogue-de-messier", "recordid": "d6e93275af7f067739c4c102723ca12bef0ba7a4", "fields": {"objet": "Open Cluster / Amas Ouvert", "const": "Sgr", "mag": 6, "decouvreur": "Messier", "distance": 4900, "image": "http://www.lasam.ca/messier/M018.JPG", "ngc": "NGC 6613", "latin_name_nom_latin": "Sagittarius", "messier": "M18", "image_url": {"mimetype": "image/jpeg", "format": "JPEG", "color_summary": ["rgba(222, 221, 221, 1.00)", "rgba(201, 199, 199, 1.00)", "rgba(183, 182, 183, 1.00)"], "filename": "M018.JPG.jpe", "width": 816, "id": "86787116516b785cd0f19c05813f27cd", "height": 1054, "thumbnail": true}, "saison": "Summer / \u00c9t\u00e9", "english_name_nom_en_anglais": "Archer", "french_name_nom_francais": "Sagittaire", "annee": "1764", "dec": "-17:06:07.1", "dimension": "9,0'", "ra": "18:19:58.49"}, "record_timestamp": "2019-03-05T10:44:29.021+01:00"},{"datasetid": "catalogue-de-messier", "recordid": "bf8a3b52d304ee597160b0b38e48a9baac7da14a", "fields": {"objet": "Open Cluster / Amas Ouvert", "const": "Sgr", "mag": 5, "decouvreur": "Messier", "distance": 4200, "image": "http://www.lasam.ca/messier/M021.JPG", "ngc": "NGC 6531", "latin_name_nom_latin": "Sagittarius", "messier": "M21", "image_url": {"mimetype": "image/jpeg", "format": "JPEG", "color_summary": ["rgba(214, 213, 213, 1.00)", "rgba(189, 187, 188, 1.00)", "rgba(184, 183, 184, 1.00)"], "filename": "M021.JPG.jpe", "width": 816, "id": "75a5abb0615e1a26f50db284646060b8", "height": 1054, "thumbnail": true}, "saison": "Summer / \u00c9t\u00e9", "english_name_nom_en_anglais": "Archer", "french_name_nom_francais": "Sagittaire", "annee": "1764", "dec": "-22:29:24.2", "dimension": "13,0'", "ra": "18:04:13.45"}, "record_timestamp": "2019-03-05T10:44:29.021+01:00"},{"datasetid": "catalogue-de-messier", "recordid": "308f7b51f801d9eb87eda212fc9312f7c6b5d5a8", "fields": {"objet": "Open Cluster / Amas Ouvert", "const": "Gem", "mag": 5, "decouvreur": "Ch\u00e9seaux", "distance": 2800, "image": "http://www.lasam.ca/messier/M035.JPG", "ngc": "NGC 2168", "latin_name_nom_latin": "Gemini", "messier": "M35", "image_url": {"mimetype": "image/jpeg", "format": "JPEG", "color_summary": ["rgba(211, 210, 211, 1.00)", "rgba(205, 204, 204, 1.00)", "rgba(199, 198, 199, 1.00)"], "filename": "M035.JPG.jpe", "width": 816, "id": "467bb231afdb84b7ef8e4e8238e12759", "height": 1054, "thumbnail": true}, "saison": "Winter / Hiver", "english_name_nom_en_anglais": "Twins", "french_name_nom_francais": "Les\u00a0G\u00e9meaux", "annee": "1746", "dec": "+24:20:19.1", "dimension": "30,0'", "ra": "06:09:05.06"}, "record_timestamp": "2019-03-05T10:44:29.021+01:00"},{"datasetid": "catalogue-de-messier", "recordid": "ce6e4ccc420e6bd76d9ebdf951011120f751ea32", "fields": {"objet": "Galaxy / Galaxie", "const": "CVn", "mag": 8, "decouvreur": "Messier", "distance": 37000000, "image": "http://www.lasam.ca/messier/M051.JPG", "ngc": "NGC 5194", "latin_name_nom_latin": "Canes Venatici", "messier": "M51", "image_url": {"mimetype": "image/jpeg", "format": "JPEG", "color_summary": ["rgba(240, 240, 240, 1.00)", "rgba(253, 252, 252, 1.00)", "rgba(250, 250, 250, 1.00)"], "filename": "M051.JPG.jpe", "width": 816, "id": "4351888ecb69e0401039ec50877e4855", "height": 1054, "thumbnail": true}, "saison": "Spring / Printemps", "english_name_nom_en_anglais": "Hound Dogs", "french_name_nom_francais": "Les\u00a0Chiens de chasse", "annee": "1773", "dec": "+47:11:42.6", "dimension": "11,0' x 7,8'", "ra": "13:29:52.71"}, "record_timestamp": "2019-03-05T10:44:29.021+01:00"},{"datasetid": "catalogue-de-messier", "recordid": "72f3b097fa8f73d84a9f5573bc4a8523dda31b47", "fields": {"objet": "Open Cluster / Amas Ouvert", "const": "Aqr", "mag": 9, "decouvreur": "Messier", "ngc": "NGC 6994", "image": "http://www.lasam.ca/messier/M073.JPG", "latin_name_nom_latin": "Aquarius", "messier": "M73", "image_url": {"mimetype": "image/jpeg", "format": "JPEG", "color_summary": ["rgba(241, 240, 240, 1.00)", "rgba(251, 251, 251, 1.00)", "rgba(249, 249, 249, 1.00)"], "filename": "M073.JPG.jpe", "width": 816, "id": "416f765b2cb6fe7cd6389c342fb72f51", "height": 1054, "thumbnail": true}, "saison": "Autumn / Automne", "english_name_nom_en_anglais": "Water Bearer", "french_name_nom_francais": "Verseau", "annee": "1780", "dec": "-12:38:07.8", "dimension": "2,8'", "ra": "20:58:55.97"}, "record_timestamp": "2019-03-05T10:44:29.021+01:00"},{"datasetid": "catalogue-de-messier", "recordid": "5da1eeaef215fb3e6f354d67f77a6e4e1368c411", "fields": {"objet": "Galaxy / Galaxie", "const": "Cet", "mag": 8, "decouvreur": "M\u00e9chain", "distance": 52000000, "image": "http://www.lasam.ca/messier/M077.JPG", "ngc": "NGC 1068", "latin_name_nom_latin": "Cetus", "messier": "M77", "image_url": {"mimetype": "image/jpeg", "format": "JPEG", "color_summary": ["rgba(241, 240, 240, 1.00)", "rgba(252, 251, 251, 1.00)", "rgba(250, 250, 250, 1.00)"], "filename": "M077.JPG.jpe", "width": 816, "id": "34ce13fe62859221f213c499054a1556", "height": 1054, "thumbnail": true}, "saison": "Autumn / Automne", "english_name_nom_en_anglais": "Sea-monster", "french_name_nom_francais": "Baleine", "annee": "1780", "dec": "-00:00:47.8", "dimension": "6,9' x 5,9'", "ra": "02:42:40.71"}, "record_timestamp": "2019-03-05T10:44:29.021+01:00"},{"datasetid": "catalogue-de-messier", "recordid": "312167088175b1aedcaf589d78110b1ae744cced", "fields": {"objet": "Reflection Nebula / N\u00e9buleuse \u00e0 r\u00e9flexion", "const": "Ori", "mag": 8, "decouvreur": "M\u00e9chain", "distance": 1630, "image": "http://www.lasam.ca/messier/M078.JPG", "ngc": "NGC 2068", "latin_name_nom_latin": "Orion", "messier": "M78", "image_url": {"mimetype": "image/jpeg", "format": "JPEG", "color_summary": ["rgba(213, 212, 212, 1.00)", "rgba(245, 244, 244, 1.00)", "rgba(248, 247, 247, 1.00)"], "filename": "M078.JPG.jpe", "width": 816, "id": "2946d192d55227c94562066d2ed4cac5", "height": 1054, "thumbnail": true}, "saison": "Winter / Hiver", "english_name_nom_en_anglais": "Orion, Hunter", "french_name_nom_francais": "Orion", "annee": "1780", "dec": "+00:04:45.5", "dimension": "8,0' x 6,0'", "ra": "05:46:45.82"}, "record_timestamp": "2019-03-05T10:44:29.021+01:00"},{"datasetid": "catalogue-de-messier", "recordid": "c96cc8d69f2c9718f0fc940e88db4d4a60bf4c14", "fields": {"objet": "Galaxy / Galaxie", "const": "UMa", "mag": 8, "decouvreur": "Bode", "distance": 8500000, "image": "http://www.lasam.ca/messier/M082.JPG", "ngc": "NGC 3034", "latin_name_nom_latin": "Ursa Major", "messier": "M82", "image_url": {"mimetype": "image/jpeg", "format": "JPEG", "color_summary": ["rgba(242, 241, 241, 1.00)", "rgba(253, 252, 252, 1.00)", "rgba(249, 248, 248, 1.00)"], "filename": "M082.JPG.jpe", "width": 816, "id": "a698c2b1317900b12c47e040eb93e70c", "height": 1054, "thumbnail": true}, "saison": "Spring / Printemps", "english_name_nom_en_anglais": "Big Bear", "french_name_nom_francais": "Grande Ourse", "annee": "1774", "dec": "+69:40:45.8", "dimension": "11,0' x 4,6'", "ra": "09:55:52.73"}, "record_timestamp": "2019-03-05T10:44:29.021+01:00"},{"datasetid": "catalogue-de-messier", "recordid": "70d12871392388489a0ef27afd589d7e4a74087c", "fields": {"objet": "Galaxy / Galaxie", "const": "Com", "mag": 9, "decouvreur": "Messier", "distance": 41000000, "image": "http://www.lasam.ca/messier/M088.JPG", "ngc": "NGC 4501", "latin_name_nom_latin": "Coma Berenices", "messier": "M88", "image_url": {"mimetype": "image/jpeg", "format": "JPEG", "color_summary": ["rgba(241, 241, 241, 1.00)", "rgba(252, 251, 251, 1.00)", "rgba(249, 248, 248, 1.00)"], "filename": "M088.JPG.jpe", "width": 816, "id": "3df1ec0bba598bdb4129a52cd48190bb", "height": 1054, "thumbnail": true}, "saison": "Spring / Printemps", "english_name_nom_en_anglais": "Hair of Berenice", "french_name_nom_francais": "Chevelure de B\u00e9r\u00e9nice", "annee": "1781", "dec": "+14:25:13.4", "dimension": "6,9' x 3,9'", "ra": "12:31:59.16"}, "record_timestamp": "2019-03-05T10:44:29.021+01:00"},{"datasetid": "catalogue-de-messier", "recordid": "ae6fda985899174e5a0d5fb27fbaff73bd2cb35a", "fields": {"objet": "Globular Cluster / Amas Globulaire", "const": "Sgr", "mag": 7, "decouvreur": "Lacaille", "distance": 23500, "image": "http://www.lasam.ca/messier/M069.JPG", "ngc": "NGC 6637", "latin_name_nom_latin": "Sagittarius", "messier": "M69", "image_url": {"mimetype": "image/jpeg", "format": "JPEG", "color_summary": ["rgba(184, 182, 183, 1.00)", "rgba(193, 191, 192, 1.00)", "rgba(219, 218, 218, 1.00)"], "filename": "M069.JPG.jpe", "width": 816, "id": "779df16a61fc20ffff7104d9e4c60a05", "height": 1054, "thumbnail": true}, "saison": "Summer / \u00c9t\u00e9", "english_name_nom_en_anglais": "Archer", "french_name_nom_francais": "Sagittaire", "annee": "1751", "dec": "-32:20:52.7", "dimension": "3,8'", "ra": "18:31:23.23"}, "record_timestamp": "2019-03-05T10:44:29.021+01:00"},{"datasetid": "catalogue-de-messier", "recordid": "bd1bb27eef17011a31adc4aea90555eef6bbb5b0", "fields": {"objet": "Planetary Nebula / N\u00e9buleuse Plan\u00e9taire", "const": "Lyr", "mag": 9, "decouvreur": "Darquier", "distance": 1410, "image": "http://www.lasam.ca/messier/M057.JPG", "ngc": "NGC 6720", "latin_name_nom_latin": "Lyra", "messier": "M57", "image_url": {"mimetype": "image/jpeg", "format": "JPEG", "color_summary": ["rgba(238, 237, 237, 1.00)", "rgba(230, 230, 230, 1.00)", "rgba(231, 230, 230, 1.00)"], "filename": "M057.JPG.jpe", "width": 816, "id": "472ec85e2d24785c404bce9bc6992a4e", "height": 1054, "thumbnail": true}, "saison": "Summer / \u00c9t\u00e9", "english_name_nom_en_anglais": "Lyre", "french_name_nom_francais": "Lyre", "annee": "1779", "dec": "+33:01:42.9", "dimension": "71''", "ra": "18:53:35.01"}, "record_timestamp": "2019-03-05T10:44:29.021+01:00"},{"datasetid": "catalogue-de-messier", "recordid": "7d320f644fc7d09c85cacc130826694118b7dea2", "fields": {"objet": "Galaxy / Galaxie", "const": "Leo", "mag": 9, "decouvreur": "M\u00e9chain", "distance": 29000000, "image": "http://www.lasam.ca/messier/M066.JPG", "ngc": "NGC 3627", "latin_name_nom_latin": "Leo", "messier": "M66", "image_url": {"mimetype": "image/jpeg", "format": "JPEG", "color_summary": ["rgba(242, 241, 241, 1.00)", "rgba(251, 251, 251, 1.00)", "rgba(250, 249, 249, 1.00)"], "filename": "M066.JPG.jpe", "width": 816, "id": "4c175ed819a386ed3a413b0091f24581", "height": 1054, "thumbnail": true}, "saison": "Spring / Printemps", "english_name_nom_en_anglais": "Lion", "french_name_nom_francais": "Lion", "annee": "1780", "dec": "+12:59:29.5", "dimension": "8,7' x 4,4'", "ra": "11:20:14.96"}, "record_timestamp": "2019-03-05T10:44:29.021+01:00"},{"datasetid": "catalogue-de-messier", "recordid": "9eac3f15615dad9a4adbb9fbbfb4e0a367ad3805", "fields": {"objet": "Open Cluster / Amas Ouvert", "const": "Cnc", "mag": 3, "distance": 520, "image": "http://www.lasam.ca/messier/M044.JPG", "ngc": "NGC 2632", "latin_name_nom_latin": "Cancer", "messier": "M44", "image_url": {"mimetype": "image/jpeg", "format": "JPEG", "color_summary": ["rgba(241, 240, 240, 1.00)", "rgba(251, 250, 250, 1.00)", "rgba(249, 249, 249, 1.00)"], "filename": "M044.JPG.jpe", "width": 816, "id": "d4caf3578fb228161b3065e9d37cc2b2", "height": 1054, "thumbnail": true}, "saison": "Spring / Printemps", "english_name_nom_en_anglais": "Crab", "french_name_nom_francais": "Cancer", "dec": "+19:40:19.4", "dimension": "70,0'", "ra": "08:40:22.20"}, "record_timestamp": "2019-03-05T10:44:29.021+01:00"},{"datasetid": "catalogue-de-messier", "recordid": "e8abdfd4f3d132a4f99f75e9ff10d508d3f2b43b", "fields": {"objet": "Galaxy / Galaxie", "const": "Com", "mag": 9, "decouvreur": "M\u00e9chain", "distance": 41000000, "image": "http://www.lasam.ca/messier/M100.JPG", "ngc": "NGC 4321", "latin_name_nom_latin": "Coma Berenices", "messier": "M100", "image_url": {"mimetype": "image/jpeg", "format": "JPEG", "color_summary": ["rgba(242, 241, 241, 1.00)", "rgba(252, 251, 251, 1.00)", "rgba(249, 248, 248, 1.00)"], "filename": "M100.JPG.jpe", "width": 816, "id": "0b5669eb3e06461e8bf429b734717e0d", "height": 1054, "thumbnail": true}, "saison": "Spring / Printemps", "english_name_nom_en_anglais": "Hair of Berenice", "french_name_nom_francais": "Chevelure de B\u00e9r\u00e9nice", "annee": "1781", "dec": "+15:49:18.5", "dimension": "6,9' x 6,2'", "ra": "12:22:54.83"}, "record_timestamp": "2019-03-05T10:44:29.021+01:00"},{"datasetid": "catalogue-de-messier", "recordid": "c1c0cf675326663246626cbb6351299afbb63c20", "fields": {"objet": "Globular Cluster / Amas Globulaire", "const": "Aqr", "mag": 9, "decouvreur": "M\u00e9chain", "distance": 62000, "image": "http://www.lasam.ca/messier/M072.JPG", "ngc": "NGC 6981", "latin_name_nom_latin": "Aquarius", "messier": "M72", "image_url": {"mimetype": "image/jpeg", "format": "JPEG", "color_summary": ["rgba(241, 240, 240, 1.00)", "rgba(251, 251, 251, 1.00)", "rgba(249, 248, 248, 1.00)"], "filename": "M072.JPG.jpe", "width": 816, "id": "7038bdf46b99d2351020ebaab7450c88", "height": 1054, "thumbnail": true}, "saison": "Autumn / Automne", "english_name_nom_en_anglais": "Water Bearer", "french_name_nom_francais": "Verseau", "annee": "1780", "dec": "-12:32:13.4", "dimension": "5,1'", "ra": "20:53:27.91"}, "record_timestamp": "2019-03-05T10:44:29.021+01:00"},{"datasetid": "catalogue-de-messier", "recordid": "f6bab809048e34b438fa77c5e142a149451094b1", "fields": {"objet": "Globular Cluster / Amas Globulaire", "const": "CVn", "mag": 6, "decouvreur": "Messier", "distance": 48500, "image": "http://www.lasam.ca/messier/M003.JPG", "ngc": "NGC 5272", "latin_name_nom_latin": "Canes Venatici", "messier": "M3", "image_url": {"mimetype": "image/jpeg", "format": "JPEG", "color_summary": ["rgba(242, 241, 241, 1.00)", "rgba(253, 253, 253, 1.00)", "rgba(250, 249, 249, 1.00)"], "filename": "M003.JPG.jpe", "width": 816, "id": "fd1a521c7991b13865e64a87cba3d496", "height": 1054, "thumbnail": true}, "saison": "Spring / Printemps", "english_name_nom_en_anglais": "Hound Dogs", "french_name_nom_francais": "Les\u00a0Chiens de chasse", "annee": "1764", "dec": "+28:22:31.6", "dimension": "18,6'", "ra": "13:42:11.23"}, "record_timestamp": "2019-03-05T10:44:29.021+01:00"},{"datasetid": "catalogue-de-messier", "recordid": "67e0d0086d756529aa16bd3a3bd5b56bf634aaab", "fields": {"objet": "Open Cluster / Amas Ouvert", "const": "Sco", "mag": 3, "decouvreur": "Ptol\u00e9m\u00e9e", "distance": 780, "image": "http://www.lasam.ca/messier/M007.JPG", "ngc": "NGC 6475", "latin_name_nom_latin": "Scorpius", "messier": "M7", "image_url": {"mimetype": "image/jpeg", "format": "JPEG", "color_summary": ["rgba(182, 181, 182, 1.00)", "rgba(186, 185, 185, 1.00)", "rgba(204, 203, 203, 1.00)"], "filename": "M007.JPG.jpe", "width": 816, "id": "b2950d9724ec8f480da8b4c0d5d5f48b", "height": 1054, "thumbnail": true}, "saison": "Summer / \u00c9t\u00e9", "english_name_nom_en_anglais": "Scorpion", "french_name_nom_francais": "Scorpion", "dec": "-34:47:34.2", "dimension": "30,0'", "ra": "17:53:51.18"}, "record_timestamp": "2019-03-05T10:44:29.021+01:00"},{"datasetid": "catalogue-de-messier", "recordid": "f9966a70c362bbee6a4bfcc080a63638b44491df", "fields": {"objet": "Globular Cluster / Amas Globulaire", "const": "Se1", "decouvreur": "Kirch", "distance": 24800, "image": "http://www.lasam.ca/messier/M005.JPG", "ngc": "NGC 5904", "messier": "M5", "image_url": {"mimetype": "image/jpeg", "format": "JPEG", "color_summary": ["rgba(241, 240, 240, 1.00)", "rgba(253, 253, 253, 1.00)", "rgba(250, 249, 250, 1.00)"], "filename": "M005.JPG.jpe", "width": 816, "id": "7370eb11bf12646584c5e5357cc2556b", "height": 1054, "thumbnail": true}, "saison": "Spring / Printemps", "mag": 5, "annee": "1702", "dec": "+02:04:57.7", "dimension": "19,9'", "ra": "15:18:33.75"}, "record_timestamp": "2019-03-05T10:44:29.021+01:00"},{"datasetid": "catalogue-de-messier", "recordid": "fb2479b25724a2834021237f7ed1cd5d6811d4f0", "fields": {"objet": "Open Cluster / Amas Ouvert", "const": "Cyg", "mag": 4, "decouvreur": "Le Gentil", "distance": 880, "image": "http://www.lasam.ca/messier/M039.JPG", "ngc": "NGC 7092", "latin_name_nom_latin": "Cygnus", "messier": "M39", "image_url": {"mimetype": "image/jpeg", "format": "JPEG", "color_summary": ["rgba(210, 210, 211, 1.00)", "rgba(203, 202, 203, 1.00)", "rgba(212, 211, 212, 1.00)"], "filename": "M039.JPG.jpe", "width": 816, "id": "71502ac0261783ada7c258f818ef13ee", "height": 1054, "thumbnail": true}, "saison": "Autumn / Automne", "english_name_nom_en_anglais": "Swan", "french_name_nom_francais": "Cygne", "annee": "1750", "dec": "+48:26:17.4", "dimension": "32,0'", "ra": "21:31:48.32"}, "record_timestamp": "2019-03-05T10:44:29.021+01:00"},{"datasetid": "catalogue-de-messier", "recordid": "c3496d3f5fe7cea72b0fe2f9baa28feaf7eff791", "fields": {"objet": "Open Cluster / Amas Ouvert", "const": "Cyg", "mag": 6, "decouvreur": "Messier", "distance": 4100, "image": "http://www.lasam.ca/messier/M029.JPG", "ngc": "NGC 6913", "latin_name_nom_latin": "Cygnus", "messier": "M29", "image_url": {"mimetype": "image/jpeg", "format": "JPEG", "color_summary": ["rgba(200, 199, 200, 1.00)", "rgba(198, 197, 199, 1.00)", "rgba(204, 203, 203, 1.00)"], "filename": "M029.JPG.jpe", "width": 816, "id": "320893eb15e78189e7c72cd38d807c23", "height": 1054, "thumbnail": true}, "saison": "Summer / \u00c9t\u00e9", "english_name_nom_en_anglais": "Swan", "french_name_nom_francais": "Cygne", "annee": "1764", "dec": "+38:30:27.6", "dimension": "7,0'", "ra": "20:23:57.77"}, "record_timestamp": "2019-03-05T10:44:29.021+01:00"},{"datasetid": "catalogue-de-messier", "recordid": "89b6602da3c4d09b73b6d2069e73756720549ea4", "fields": {"objet": "Globular Cluster / Amas Globulaire", "const": "Oph", "mag": 8, "decouvreur": "M\u00e9chain", "distance": 19200, "image": "http://www.lasam.ca/messier/M107.JPG", "ngc": "NGC 6171", "latin_name_nom_latin": "Ophiuchus", "messier": "M107", "image_url": {"mimetype": "image/jpeg", "format": "JPEG", "color_summary": ["rgba(242, 241, 241, 1.00)", "rgba(248, 247, 247, 1.00)", "rgba(222, 222, 223, 1.00)"], "filename": "M107.JPG.jpe", "width": 816, "id": "f309fd24fe9cf7fc97aad714d940508e", "height": 1054, "thumbnail": true}, "saison": "Summer / \u00c9t\u00e9", "english_name_nom_en_anglais": "Serpent Holder", "french_name_nom_francais": "Ophiuchus", "annee": "1782", "dec": "-13:03:13.1", "dimension": "7,8'", "ra": "16:32:31.92"}, "record_timestamp": "2019-03-05T10:44:29.021+01:00"},{"datasetid": "catalogue-de-messier", "recordid": "24b23c418b9688e6d57e5cdfa76632f512487449", "fields": {"objet": "Galaxy / Galaxie", "const": "UMa", "mag": 10, "decouvreur": "M\u00e9chain", "distance": 23500000, "image": "http://www.lasam.ca/messier/M108.JPG", "ngc": "NGC 3556", "latin_name_nom_latin": "Ursa Major", "messier": "M108", "image_url": {"mimetype": "image/jpeg", "format": "JPEG", "color_summary": ["rgba(240, 239, 239, 1.00)", "rgba(252, 252, 252, 1.00)", "rgba(250, 250, 250, 1.00)"], "filename": "M108.JPG.jpe", "width": 816, "id": "5403cbb65a974f52aea06e01e8efabea", "height": 1054, "thumbnail": true}, "saison": "Spring / Printemps", "english_name_nom_en_anglais": "Big Bear", "french_name_nom_francais": "Grande Ourse", "annee": "1782", "dec": "+55:40:26.8", "dimension": "8,3' x 2,5'", "ra": "11:11:30.97"}, "record_timestamp": "2019-03-05T10:44:29.021+01:00"}]